Workbook
Name UPDATE: 'DATA SHEET'!$E$1

Sheet DATA SHEET
A1: COMPANY NAME | B1: TATA MOTORS LTD | E1: =IF(B2<>B3,"A NEW VERSION OF THE WORKSHEET IS AVAILABLE","")
A2: LATEST VERSION | B2: 2.1 | E2: PLEASE DO NOT MAKE ANY CHANGES TO THIS SHEET
A3: CURRENT VERSION | B3: 2.1
A5: META
A6: Number of shares | B6: =IF(B9>0,B9/B8,0) -> 0
A7: Face Value | B7: 2
A8: Current Price | B8: 697.3
A9: Market Capitalization | B9: 256689.37
A15: PROFIT & LOSS
A16: Report Date | B16: 42094 | C16: 42460 | D16: 42825 | E16: 43190 | F16: 43555 | G16: 43921 | H16: 44286 | I16: 44651 | J16: 45016 | K16: 45382
A17: Sales | B17: 263158.98 | C17: 273045.6 | D17: 269692.51 | E17: 291550.48 | F17: 301938.4 | G17: 261067.97 | H17: 249794.75 | I17: 278453.62 | J17: 345966.97 | K17: 437927.77
A18: Raw Material Cost | B18: 163250.36 | C18: 166134.01 | D18: 173294.08 | E18: 187896.58 | F18: 194267.91 | G18: 164899.82 | H18: 153607.36 | I18: 179295.33 | J18: 231251.26 | K18: 274321.23
A19: Change in Inventory | B19: 3330.35 | C19: 2750.99 | D19: 7399.92 | E19: 2046.58 | F19: -2053.28 | G19: -2231.19 | H19: -4684.16 | I19: -1590.49 | J19: 4781.62 | K19: 1565.53
A20: Power and Fuel | B20: 1121.75 | C20: 1143.63 | D20: 1159.82 | E20: 1308.08 | F20: 1585.93 | G20: 1264.95 | H20: 1112.87 | I20: 2178.29 | J20: 2513.33 | K20: 2195.12
A21: Other Mfr. Exp | B21: 16173.17 | C21: 12101.53 | D21: 10067.37 | E21: 10971.66 | F21: 11694.54 | G21: 11541.51 | H21: 8273.17 | I21: 9427.38 | J21: 11765.97 | K21: 17114.33
A22: Employee Cost | B22: 25641.95 | C22: 28880.89 | D22: 28332.89 | E22: 30300.09 | F22: 33243.87 | G22: 30438.6 | H22: 27648.48 | I22: 30808.52 | J22: 33654.7 | K22: 42486.64
A23: Selling and admin | B23: 23603.01 | C23: 21991.9 | D23: 30039.38 | E23: 31004.58 | F23: 32719.8 | G23: 29248.32 | H23: 23015.79 | I23: 29205.4 | J23: 34839.19 | K23: 42765.33
A24: Other Expenses | B24: -2539.56 | C24: 7149.38 | D24: 4610.2 | E24: 658.39 | F24: 1708.74 | G24: 3456.51 | H24: -834.51 | I24: 1228.12 | J24: 4908.34 | K24: 1072.31
A25: Other Income | B25: 714.03 | C25: -2669.62 | D25: 1869.1 | E25: 5932.73 | F25: -26686.25 | G25: 101.71 | H25: -11117.83 | I25: 2424.05 | J25: 6663.97 | K25: 5672.66
A26: Depreciation | B26: 13388.63 | C26: 16710.78 | D26: 17904.99 | E26: 21553.59 | F26: 23590.63 | G26: 21425.43 | H26: 23546.71 | I26: 24835.69 | J26: 24860.36 | K26: 27270.13
A27: Interest | B27: 4861.49 | C27: 4889.08 | D27: 4238.01 | E27: 4681.79 | F27: 5758.6 | G27: 7243.33 | H27: 8097.17 | I27: 9311.86 | J27: 10225.48 | K27: 9985.76
... A30: Net profit | B30: 13986.29 | C30: 11579.31 | D30: 7454.36 | E30: 8988.91 | F30: -28826.23 | G30: -12070.85 | H30: -13451.39 | I30: -11441.47 | J30: 2414.29 | K30: 31399.09
A31: Dividend Amount | C31: 67.92 | J31: 766.02 | K31: 2299.5
A40: Quarters
A41: Report Date | B41: 44834 | C41: 44926 | D41: 45016 | E41: 45107 | F41: 45199 | G41: 45291 | H41: 45382 | I41: 45473 | J41: 45565 | K41: 45657
A42: Sales | B42: 79611.37 | C42: 88488.59 | D42: 105932.35 | E42: 102236 | F42: 105129 | G42: 110577 | H42: 119986 | I42: 108048 | J42: 101450 | K42: 113575
A43: Expenses | B43: 74039.06 | C43: 77668.35 | D43: 92817.95 | E43: 89019 | F43: 91362 | G43: 95159 | H43: 102851 | I43: 92263 | J43: 89291 | K43: 100532
A44: Other Income | B44: 1351.14 | C44: 1129.98 | D44: 1452.86 | E44: 895 | F44: 1557 | G44: 1604 | H44: 1619 | I44: 1747 | J44: 1647 | K44: 1764
A45: Depreciation | B45: 5897.34 | C45: 6071.78 | D45: 7050.2 | E45: 6633 | F45: 6637 | G45: 6850 | H45: 7151 | I45: 6574 | J45: 6005 | K45: 5408
A46: Interest | B46: 2487.26 | C46: 2675.83 | D46: 2641.67 | E46: 2615 | F46: 2652 | G46: 2485 | H46: 2234 | I46: 2088 | J46: 2034 | K46: 1725
A47: Profit before tax | B47: -1461.15 | C47: 3202.61 | D47: 4875.39 | E47: 4864 | F47: 6035 | G47: 7687 | H47: 9369 | I47: 8870 | J47: 5767 | K47: 7674
A48: Tax | B48: -457.08 | C48: 262.83 | D48: -620.65 | E48: 1563 | F48: 2203 | G48: 542 | H48: -8160 | I48: 3178 | J48: 2317 | K48: 2096
A49: Net profit | B49: -944.61 | C49: 2957.71 | D49: 5407.79 | E49: 3203 | F49: 3764 | G49: 7025 | H49: 17407 | I49: 5566 | J49: 3343 | K49: 5451
A50: Operating Profit | B50: 5572.31 | C50: 10820.24 | D50: 13114.4 | E50: 13217 | F50: 13767 | G50: 15418 | H50: 17135 | I50: 15785 | J50: 12159 | K50: 13043
A55: BALANCE SHEET
A56: Report Date | B56: 42094 | C56: 42460 | D56: 42825 | E56: 43190 | F56: 43555 | G56: 43921 | H56: 44286 | I56: 44651 | J56: 45016 | K56: 45382
A57: Equity Share Capital | B57: 643.78 | C57: 679.18 | D57: 679.22 | E57: 679.22 | F57: 679.22 | G57: 719.54 | H57: 765.81 | I57: 765.88 | J57: 766.02 | K57: 766.5
A58: Reserves | B58: 55618.14 | C58: 78273.23 | D58: 57382.67 | E58: 94748.69 | F58: 59500.34 | G58: 62358.99 | H58: 54480.91 | I58: 43795.36 | J58: 44555.77 | K58: 84151.52
A59: Borrowings | B59: 73610.39 | C59: 69359.96 | D59: 78603.98 | E59: 88950.47 | F59: 106175.34 | G59: 124787.64 | H59: 142130.57 | I59: 146449.03 | J59: 134113.44 | K59: 107262.5
A60: Other Liabilities | B60: 107442.48 | C60: 114871.75 | D60: 135914.49 | E60: 142813.43 | F60: 139348.59 | G60: 132313.22 | H60: 144192.62 | I60: 138051.22 | J60: 155239.2 | K60: 177340.09
A61: Total | B61: 237314.79 | C61: 263184.12 | D61: 272580.36 | E61: 327191.81 | F61: 305703.49 | G61: 320179.39 | H61: 341569.91 | I61: 329061.49 | J61: 334674.43 | K61: 369520.61
A62: Net Block | B62: 88479.49 | C62: 107231.76 | D62: 95944.08 | E62: 121413.86 | F62: 111234.47 | G62: 127107.14 | H62: 138707.61 | I62: 138855.45 | J62: 132079.76 | K62: 121285.46
A63: Capital Work in Progress | B63: 28640.09 | C63: 25918.94 | D63: 33698.84 | E63: 40033.5 | F63: 31883.84 | G63: 35622.29 | H63: 20963.93 | I63: 10251.09 | J63: 14274.5 | K63: 35698.43
A64: Investments | B64: 15336.74 | C64: 23767.02 | D64: 20337.92 | E64: 20812.75 | F64: 15770.72 | G64: 16308.48 | H64: 24620.28 | I64: 29379.53 | J64: 26379.16 | K64: 22971.07
A65: Other Assets | B65: 104858.47 | C65: 106266.4 | D65: 122599.52 | E65: 144931.7 | F65: 146814.46 | G65: 141141.48 | H65: 157278.09 | I65: 150575.42 | J65: 161941.01 | K65: 189565.65
A66: Total | B66: 237314.79 | C66: 263184.12 | D66: 272580.36 | E66: 327191.81 | F66: 305703.49 | G66: 320179.39 | H66: 341569.91 | I66: 329061.49 | J66: 334674.43 | K66: 369520.61
A67: Receivables | B67: 12579.2 | C67: 13570.91 | D67: 14075.55 | E67: 19893.3 | F67: 18996.17 | G67: 11172.69 | H67: 12679.08 | I67: 12442.12 | J67: 15737.97 | K67: 16951.81
... A70: No. of Equity Shares | B70: 3218930067 | C70: 3395930306 | D70: 3396100719 | E70: 3396100719 | F70: 3396100719 | G70: 3597726185 | H70: 3829060661 | I70: 3829414903 | J70: 3830097221 | K70: 3832491897
A71: New Bonus Shares
A72: Face value | B72: 2 | C72: 2 | D72: 2 | E72: 2 | F72: 2 | G72: 2 | H72: 2 | I72: 2 | J72: 2 | K72: 2
A80: CASH FLOW:
A81: Report Date | B81: 42094 | C81: 42460 | D81: 42825 | E81: 43190 | F81: 43555 | G81: 43921 | H81: 44286 | I81: 44651 | J81: 45016 | K81: 45382
A82: Cash from Operating Activity | B82: 35531.26 | C82: 37899.54 | D82: 30199.25 | E82: 23857.42 | F82: 18890.75 | G82: 26632.94 | H82: 29000.51 | I82: 14282.83 | J82: 35388.01 | K82: 67915.36
A83: Cash from Investing Activity | B83: -36232.35 | C83: -36693.9 | D83: -39571.4 | E83: -25139.14 | F83: -20878.07 | G83: -33114.55 | H83: -25672.5 | I83: -4443.66 | J83: -15417.17 | K83: -22781.56
A84: Cash from Financing Activity | B84: 5201.44 | C84: -3795.12 | D84: 6205.3 | E84: 2011.71 | F84: 8830.37 | G84: 3389.61 | H84: 9904.2 | I84: -3380.17 | J84: -26242.9 | K84: -37005.99
A85: Net Cash Flow | B85: 4500.35 | C85: -2589.48 | D85: -3166.85 | E85: 729.99 | F85: 6843.05 | G85: -3092 | H85: 13232.21 | I85: 6459 | J85: -6272.06 | K85: 8127.81
A90: PRICE: | B90: 544.37 | C90: 386.6 | D90: 465.85 | E90: 326.85 | F90: 174.25 | G90: 71.05 | H90: 301.8 | I90: 433.75 | J90: 420.8 | K90: 992.8
A92: DERIVED:
A93: Adjusted Equity Shares in Cr | B93: 288.74 | C93: 288.72 | D93: 288.73 | E93: 288.73 | F93: 288.73 | G93: 308.9 | H93: 332.03 | I93: 332.07 | J93: 332.13 | K93: 332.37

Sheet HISTORICAL FS
B2: ="Historical Financial Data - "&'DATA SHEET'!B1 -> Historical Financial Data - TATA MOTORS LTD
B3: Years | C3: ='DATA SHEET'!B16 -> 42094 | D3: ='DATA SHEET'!C16 -> 42460 | E3: ='DATA SHEET'!D16 -> 42825 | F3: ='DATA SHEET'!E16 -> 43190 | G3: ='DATA SHEET'!F16 -> 43555 | H3: ='DATA SHEET'!G16 -> 43921 | I3: ='DATA SHEET'!H16 -> 44286 | J3: ='DATA SHEET'!I16 -> 44651 | ... L3: ='DATA SHEET'!K16 -> 45382 | M3: LTM
A4: # | B4: INCOME STATEMENT
B5: SALES | C5: =IFERROR('DATA SHEET'!B17,0) -> 263158.98 | D5: =IFERROR('DATA SHEET'!C17,0) -> 273045.6 | E5: =IFERROR('DATA SHEET'!D17,0) -> 269692.51 | F5: =IFERROR('DATA SHEET'!E17,0) -> 291550.48 | G5: =IFERROR('DATA SHEET'!F17,0) -> 301938.4 | H5: =IFERROR('DATA SHEET'!G17,0) -> 261067.97 | I5: =IFERROR('DATA SHEET'!H17,0) -> 249794.75 | J5: =IFERROR('DATA SHEET'!I17,0) -> 278453.62 | ... L5: =IFERROR('DATA SHEET'!K17,0) -> 437927.77 | M5: =IFERROR(SUM('DATA SHEET'!H42:K42),0) -> 443059
B6: SALES GROWTH | D6: =D5/C5-1 -> 0.037569001 | E6: =E5/D5-1 -> -0.01228033 | F6: =F5/E5-1 -> 0.081047746 | G6: =G5/F5-1 -> 0.035629919 | H6: =H5/G5-1 -> -0.13536016 | I6: =I5/H5-1 -> -0.043181168 | J6: =J5/I5-1 -> 0.11472967 | K6: =K5/J5-1 -> 0.24245815 | L6: =L5/K5-1 -> 0.26580803
B8: COGS | C8: =IFERROR(SUM('DATA SHEET'!B18,'DATA SHEET'!B20,'DATA SHEET'!B21,'DATA SHEET'!B22)-1*'DATA SHEET'!B19,0) -> 202856.88 | D8: =IFERROR(SUM('DATA SHEET'!C18,'DATA SHEET'!C20,'DATA SHEET'!C21,'DATA SHEET'!C22)-1*'DATA SHEET'!C19,0) -> 205509.07 | E8: =IFERROR(SUM('DATA SHEET'!D18,'DATA SHEET'!D20,'DATA SHEET'!D21,'DATA SHEET'!D22)-1*'DATA SHEET'!D19,0) -> 205454.24 | F8: =IFERROR(SUM('DATA SHEET'!E18,'DATA SHEET'!E20,'DATA SHEET'!E21,'DATA SHEET'!E22)-1*'DATA SHEET'!E19,0) -> 228429.83 | G8: =IFERROR(SUM('DATA SHEET'!F18,'DATA SHEET'!F20,'DATA SHEET'!F21,'DATA SHEET'!F22)-1*'DATA SHEET'!F19,0) -> 242845.53 | H8: =IFERROR(SUM('DATA SHEET'!G18,'DATA SHEET'!G20,'DATA SHEET'!G21,'DATA SHEET'!G22)-1*'DATA SHEET'!G19,0) -> 210376.07 | I8: =IFERROR(SUM('DATA SHEET'!H18,'DATA SHEET'!H20,'DATA SHEET'!H21,'DATA SHEET'!H22)-1*'DATA SHEET'!H19,0) -> 195326.04 | J8: =IFERROR(SUM('DATA SHEET'!I18,'DATA SHEET'!I20,'DATA SHEET'!I21,'DATA SHEET'!I22)-1*'DATA SHEET'!I19,0) -> 223300.01 | ... L8: =IFERROR(SUM('DATA SHEET'!K18,'DATA SHEET'!K20,'DATA SHEET'!K21,'DATA SHEET'!K22)-1*'DATA SHEET'!K19,0) -> 334551.79
B9: COGS % SALES | C9: =C8/C5 -> 0.77085297 | D9: =D8/D5 -> 0.75265476 | E9: =E8/E5 -> 0.76180922 | F9: =F8/F5 -> 0.7835001 | G9: =G8/G5 -> 0.80428833 | H9: =H8/H5 -> 0.80582873 | I9: =I8/I5 -> 0.78194614 | J9: =J8/J5 -> 0.80192892 | ... L9: =L8/L5 -> 0.76394285
B11: GROSS PROFIT | C11: =C5-C8 -> 60302.1 | D11: =D5-D8 -> 67536.53 | E11: =E5-E8 -> 64238.27 | F11: =F5-F8 -> 63120.65 | G11: =G5-G8 -> 59092.87 | H11: =H5-H8 -> 50691.9 | I11: =I5-I8 -> 54468.71 | J11: =J5-J8 -> 55153.61 | ... L11: =L5-L8 -> 103375.98
B12: GROSS PROFIT MARGIN
B14: SELLING AND GEN. EXP | C14: =IFERROR(SUM('DATA SHEET'!B23,'DATA SHEET'!B24),0) -> 21063.45 | D14: =IFERROR(SUM('DATA SHEET'!C23,'DATA SHEET'!C24),0) -> 29141.28 | E14: =IFERROR(SUM('DATA SHEET'!D23,'DATA SHEET'!D24),0) -> 34649.58 | F14: =IFERROR(SUM('DATA SHEET'!E23,'DATA SHEET'!E24),0) -> 31662.97 | G14: =IFERROR(SUM('DATA SHEET'!F23,'DATA SHEET'!F24),0) -> 34428.54 | H14: =IFERROR(SUM('DATA SHEET'!G23,'DATA SHEET'!G24),0) -> 32704.83 | I14: =IFERROR(SUM('DATA SHEET'!H23,'DATA SHEET'!H24),0) -> 22181.28 | J14: =IFERROR(SUM('DATA SHEET'!I23,'DATA SHEET'!I24),0) -> 30433.52 | ... L14: =IFERROR(SUM('DATA SHEET'!K23,'DATA SHEET'!K24),0) -> 43837.64
B15: S & G % SALES | C15: =C14/C5 -> 0.08004078 | D15: =D14/D5 -> 0.10672679 | E15: =E14/E5 -> 0.1284781 | F15: =F14/F5 -> 0.10860202 | G15: =G14/G5 -> 0.11402505 | H15: =H14/H5 -> 0.12527324 | I15: =I14/I5 -> 0.088798023 | J15: =J14/J5 -> 0.10929475 | ... L15: =L14/L5 -> 0.10010244
B17: EBITDA | C17: =C11-C14 -> 39238.65 | D17: =D11-D14 -> 38395.25 | E17: =E11-E14 -> 29588.69 | F17: =F11-F14 -> 31457.68 | G17: =G11-G14 -> 24664.33 | H17: =H11-H14 -> 17987.07 | I17: =I11-I14 -> 32287.43 | J17: =J11-J14 -> 24720.09 | ... L17: =L11-L14 -> 59538.34
B18: EBITDA MARGIN | C18: =C17/C5 -> 0.14910626 | D18: =D17/D5 -> 0.14061845 | E18: =E17/E5 -> 0.10971269 | F18: =F17/F5 -> 0.10789788 | G18: =G17/G5 -> 0.081686629 | H18: =H17/H5 -> 0.068898034 | I18: =I17/I5 -> 0.12925584 | J18: =J17/J5 -> 0.088776328 | ... L18: =L17/L5 -> 0.1359547
B20: INTEREST | C20: =IFERROR('DATA SHEET'!B27,0) -> 4861.49 | D20: =IFERROR('DATA SHEET'!C27,0) -> 4889.08 | E20: =IFERROR('DATA SHEET'!D27,0) -> 4238.01 | F20: =IFERROR('DATA SHEET'!E27,0) -> 4681.79 | G20: =IFERROR('DATA SHEET'!F27,0) -> 5758.6 | H20: =IFERROR('DATA SHEET'!G27,0) -> 7243.33 | I20: =IFERROR('DATA SHEET'!H27,0) -> 8097.17 | J20: =IFERROR('DATA SHEET'!I27,0) -> 9311.86 | ... L20: =IFERROR('DATA SHEET'!K27,0) -> 9985.76
B21: INTEREST % SALES | C21: =C20/C5 -> 0.018473586 | D21: =D20/D5 -> 0.017905727 | E21: =E20/E5 -> 0.01571423 | F21: =F20/F5 -> 0.016058248 | G21: =G20/G5 -> 0.019072102 | H21: =H20/H5 -> 0.027744997 | I21: =I20/I5 -> 0.032415293 | J21: =J20/J5 -> 0.033441332 | ... L21: =L20/L5 -> 0.022802299
B23: DEPRICIATION | C23: =IFERROR('DATA SHEET'!B26,0) -> 13388.63 | D23: =IFERROR('DATA SHEET'!C26,0) -> 16710.78 | E23: =IFERROR('DATA SHEET'!D26,0) -> 17904.99 | F23: =IFERROR('DATA SHEET'!E26,0) -> 21553.59 | G23: =IFERROR('DATA SHEET'!F26,0) -> 23590.63 | H23: =IFERROR('DATA SHEET'!G26,0) -> 21425.43 | I23: =IFERROR('DATA SHEET'!H26,0) -> 23546.71 | J23: =IFERROR('DATA SHEET'!I26,0) -> 24835.69 | ... L23: =IFERROR('DATA SHEET'!K26,0) -> 27270.13
B24: DEP % SALES | C24: =C23/C5 -> 0.050876584 | D24: =D23/D5 -> 0.061201426 | E24: =E23/E5 -> 0.066390387 | F24: =F23/F5 -> 0.073927472 | G24: =G23/G5 -> 0.078130605 | H24: =H23/H5 -> 0.082068398 | I24: =I23/I5 -> 0.094264231 | J24: =J23/J5 -> 0.089191478 | ... L24: =L23/L5 -> 0.06227084
B26: EARNING BEFORE TAX | C26: =IFERROR('DATA SHEET'!B28,0) -> 21702.56 | D26: =IFERROR('DATA SHEET'!C28,0) -> 14125.77 | E26: =IFERROR('DATA SHEET'!D28,0) -> 9314.79 | F26: =IFERROR('DATA SHEET'!E28,0) -> 11155.03 | G26: =IFERROR('DATA SHEET'!F28,0) -> -31371.15 | H26: =IFERROR('DATA SHEET'!G28,0) -> -10579.98 | I26: =IFERROR('DATA SHEET'!H28,0) -> -10474.28 | J26: =IFERROR('DATA SHEET'!I28,0) -> -7003.41 | ... L26: =IFERROR('DATA SHEET'!K28,0) -> 27955.11
B27: EBT % SALES | C27: =C26/C5 -> 0.082469388 | D27: =D26/D5 -> 0.051734106 | E27: =E26/E5 -> 0.034538557 | F27: =F26/F5 -> 0.038261059 | G27: =G26/G5 -> -0.10389917 | H27: =H26/H5 -> -0.040525768 | I27: =I26/I5 -> -0.041931546 | J27: =J26/J5 -> -0.025151083 | ... L27: =L26/L5 -> 0.063834979
B29: TAX | C29: =IFERROR('DATA SHEET'!B29,0) -> 7642.91 | D29: =IFERROR('DATA SHEET'!C29,0) -> 3025.05 | E29: =IFERROR('DATA SHEET'!D29,0) -> 3251.23 | F29: =IFERROR('DATA SHEET'!E29,0) -> 4341.93 | G29: =IFERROR('DATA SHEET'!F29,0) -> -2437.45 | H29: =IFERROR('DATA SHEET'!G29,0) -> 395.25 | I29: =IFERROR('DATA SHEET'!H29,0) -> 2541.86 | J29: =IFERROR('DATA SHEET'!I29,0) -> 4231.29 | ... L29: =IFERROR('DATA SHEET'!K29,0) -> -3851.64
B30: EFFECTIVE TAX RATE | C30: =C29/C26 -> 0.35216629 | D30: =D29/D26 -> 0.21415116 | E30: =E29/E26 -> 0.34903954 | F30: =F29/F26 -> 0.38923517 | G30: =G29/G26 -> 0.077697184 | H30: =H29/H26 -> -0.037358294 | I30: =I29/I26 -> -0.24267635 | J30: =J29/J26 -> -0.60417568 | ... L30: =L29/L26 -> -0.13777946
B32: NET PROFIT | C32: =C26-C29 -> 14059.65 | D32: =D26-D29 -> 11100.72 | E32: =E26-E29 -> 6063.56 | F32: =F26-F29 -> 6813.1 | G32: =G26-G29 -> -28933.7 | H32: =H26-H29 -> -10975.23 | I32: =I26-I29 -> -13016.14 | J32: =J26-J29 -> -11234.7 | ... L32: =L26-L29 -> 31806.75
B33: NET MARGIN | C33: =C32/C5 -> 0.05342645 | D33: =D32/D5 -> 0.040655187 | E33: =E32/E5 -> 0.022483235 | F33: =F32/F5 -> 0.023368509 | G33: =G32/G5 -> -0.0958265 | H33: =H32/H5 -> -0.042039742 | I33: =I32/I5 -> -0.05210734 | J33: =J32/J5 -> -0.040346755 | ... L33: =L32/L5 -> 0.072630128
B35: No. of Equity Shareholders Outstanding | C35: =IFERROR('DATA SHEET'!B93,0) -> 288.74 | D35: =IFERROR('DATA SHEET'!C93,0) -> 288.72 | E35: =IFERROR('DATA SHEET'!D93,0) -> 288.73 | F35: =IFERROR('DATA SHEET'!E93,0) -> 288.73 | G35: =IFERROR('DATA SHEET'!F93,0) -> 288.73 | H35: =IFERROR('DATA SHEET'!G93,0) -> 308.9 | I35: =IFERROR('DATA SHEET'!H93,0) -> 332.03 | J35: =IFERROR('DATA SHEET'!I93,0) -> 332.07 | ... L35: =IFERROR('DATA SHEET'!K93,0) -> 332.37
B37: EPS | C37: =C32/C35 -> 48.693115 | D37: =D32/D35 -> 38.448047 | E37: =E32/E35 -> 21.000797 | F37: =F32/F35 -> 23.596786 | G37: =G32/G35 -> -100.21023 | H37: =H32/H35 -> -35.530042 | I37: =I32/I35 -> -39.201699 | J37: =J32/J35 -> -33.832325 | ... L37: =L32/L35 -> 95.696814
B38: EPS GROWTH
B39: DPS | C39: =IFERROR('DATA SHEET'!B31/'HISTORICAL FS'!C35,0) -> 0 | D39: =IFERROR('DATA SHEET'!C31/'HISTORICAL FS'!D35,0) -> 0.23524522 | E39: =IFERROR('DATA SHEET'!D31/'HISTORICAL FS'!E35,0) -> 0 | F39: =IFERROR('DATA SHEET'!E31/'HISTORICAL FS'!F35,0) -> 0 | G39: =IFERROR('DATA SHEET'!F31/'HISTORICAL FS'!G35,0) -> 0 | H39: =IFERROR('DATA SHEET'!G31/'HISTORICAL FS'!H35,0) -> 0 | I39: =IFERROR('DATA SHEET'!H31/'HISTORICAL FS'!I35,0) -> 0 | J39: =IFERROR('DATA SHEET'!I31/'HISTORICAL FS'!J35,0) -> 0 | ... L39: =IFERROR('DATA SHEET'!K31/'HISTORICAL FS'!L35,0) -> 6.9184944
B40: DPS RATIO | C40: =IFERROR(C39/C37,0) -> 0 | D40: =IFERROR(D39/D37,0) -> 0.006118522 | E40: =IFERROR(E39/E37,0) -> 0 | F40: =IFERROR(F39/F37,0) -> 0 | G40: =IFERROR(G39/G37,0) -> 0 | H40: =IFERROR(H39/H37,0) -> 0 | I40: =IFERROR(I39/I37,0) -> 0 | J40: =IFERROR(J39/J37,0) -> 0 | ... L40: =IFERROR(L39/L37,0) -> 0.072295975
B42: RETAINED EARNING | C42: =IFERROR(1-C40,0) -> 1 | D42: =IFERROR(1-D40,0) -> 0.99388148 | E42: =IFERROR(1-E40,0) -> 1 | F42: =IFERROR(1-F40,0) -> 1 | G42: =IFERROR(1-G40,0) -> 1 | H42: =IFERROR(1-H40,0) -> 1 | I42: =IFERROR(1-I40,0) -> 1 | J42: =IFERROR(1-J40,0) -> 1 | ... L42: =IFERROR(1-L40,0) -> 0.92770403
C43: =IFERROR(IF(C37>C39,1-C40,0),0) -> 1 | D43: =IFERROR(IF(D37>D39,1-D40,0),0) -> 0.99388148 | E43: =IFERROR(IF(E37>E39,1-E40,0),0) -> 1 | F43: =IFERROR(IF(F37>F39,1-F40,0),0) -> 1 | G43: =IFERROR(IF(G37>G39,1-G40,0),0) -> 0 | H43: =IFERROR(IF(H37>H39,1-H40,0),0) -> 0 | I43: =IFERROR(IF(I37>I39,1-I40,0),0) -> 0 | J43: =IFERROR(IF(J37>J39,1-J40,0),0) -> 0 | ... L43: =IFERROR(IF(L37>L39,1-L40,0),0) -> 0.92770403
A45: # | B45: BALANCE SHEET
B46: Equity Share Capital | C46: =IFERROR('DATA SHEET'!B57,0) -> 643.78 | D46: =IFERROR('DATA SHEET'!C57,0) -> 679.18 | E46: =IFERROR('DATA SHEET'!D57,0) -> 679.22 | F46: =IFERROR('DATA SHEET'!E57,0) -> 679.22 | G46: =IFERROR('DATA SHEET'!F57,0) -> 679.22 | H46: =IFERROR('DATA SHEET'!G57,0) -> 719.54 | I46: =IFERROR('DATA SHEET'!H57,0) -> 765.81 | J46: =IFERROR('DATA SHEET'!I57,0) -> 765.88 | ... L46: =IFERROR('DATA SHEET'!K57,0) -> 766.5
B47: Reserves | C47: =IFERROR('DATA SHEET'!B58,0) -> 55618.14 | D47: =IFERROR('DATA SHEET'!C58,0) -> 78273.23 | E47: =IFERROR('DATA SHEET'!D58,0) -> 57382.67 | F47: =IFERROR('DATA SHEET'!E58,0) -> 94748.69 | G47: =IFERROR('DATA SHEET'!F58,0) -> 59500.34 | H47: =IFERROR('DATA SHEET'!G58,0) -> 62358.99 | I47: =IFERROR('DATA SHEET'!H58,0) -> 54480.91 | J47: =IFERROR('DATA SHEET'!I58,0) -> 43795.36 | ... L47: =IFERROR('DATA SHEET'!K58,0) -> 84151.52
B48: Borrowings | C48: =IFERROR('DATA SHEET'!B59,0) -> 73610.39 | D48: =IFERROR('DATA SHEET'!C59,0) -> 69359.96 | E48: =IFERROR('DATA SHEET'!D59,0) -> 78603.98 | F48: =IFERROR('DATA SHEET'!E59,0) -> 88950.47 | G48: =IFERROR('DATA SHEET'!F59,0) -> 106175.34 | H48: =IFERROR('DATA SHEET'!G59,0) -> 124787.64 | I48: =IFERROR('DATA SHEET'!H59,0) -> 142130.57 | J48: =IFERROR('DATA SHEET'!I59,0) -> 146449.03 | ... L48: =IFERROR('DATA SHEET'!K59,0) -> 107262.5
B49: Other Liabilities | C49: =IFERROR('DATA SHEET'!B60,0) -> 107442.48 | D49: =IFERROR('DATA SHEET'!C60,0) -> 114871.75 | E49: =IFERROR('DATA SHEET'!D60,0) -> 135914.49 | F49: =IFERROR('DATA SHEET'!E60,0) -> 142813.43 | G49: =IFERROR('DATA SHEET'!F60,0) -> 139348.59 | H49: =IFERROR('DATA SHEET'!G60,0) -> 132313.22 | I49: =IFERROR('DATA SHEET'!H60,0) -> 144192.62 | J49: =IFERROR('DATA SHEET'!I60,0) -> 138051.22 | ... L49: =IFERROR('DATA SHEET'!K60,0) -> 177340.09
B50: Total Liabilities | C50: =SUM(C46:C49) -> 237314.79 | D50: =SUM(D46:D49) -> 263184.12 | E50: =SUM(E46:E49) -> 272580.36 | F50: =SUM(F46:F49) -> 327191.81 | G50: =SUM(G46:G49) -> 305703.49 | H50: =SUM(H46:H49) -> 320179.39 | I50: =SUM(I46:I49) -> 341569.91 | J50: =SUM(J46:J49) -> 329061.49 | ... L50: =SUM(L46:L49) -> 369520.61
B52: Fixed Asset Net Block | C52: =IFERROR('DATA SHEET'!B62,0) -> 88479.49 | D52: =IFERROR('DATA SHEET'!C62,0) -> 107231.76 | E52: =IFERROR('DATA SHEET'!D62,0) -> 95944.08 | F52: =IFERROR('DATA SHEET'!E62,0) -> 121413.86 | G52: =IFERROR('DATA SHEET'!F62,0) -> 111234.47 | H52: =IFERROR('DATA SHEET'!G62,0) -> 127107.14 | I52: =IFERROR('DATA SHEET'!H62,0) -> 138707.61 | J52: =IFERROR('DATA SHEET'!I62,0) -> 138855.45 | ... L52: =IFERROR('DATA SHEET'!K62,0) -> 121285.46
B53: Capital Work in Progress | C53: =IFERROR('DATA SHEET'!B63,0) -> 28640.09 | D53: =IFERROR('DATA SHEET'!C63,0) -> 25918.94 | E53: =IFERROR('DATA SHEET'!D63,0) -> 33698.84 | F53: =IFERROR('DATA SHEET'!E63,0) -> 40033.5 | G53: =IFERROR('DATA SHEET'!F63,0) -> 31883.84 | H53: =IFERROR('DATA SHEET'!G63,0) -> 35622.29 | I53: =IFERROR('DATA SHEET'!H63,0) -> 20963.93 | J53: =IFERROR('DATA SHEET'!I63,0) -> 10251.09 | ... L53: =IFERROR('DATA SHEET'!K63,0) -> 35698.43
B54: Investments | C54: =IFERROR('DATA SHEET'!B64,0) -> 15336.74 | D54: =IFERROR('DATA SHEET'!C64,0) -> 23767.02 | E54: =IFERROR('DATA SHEET'!D64,0) -> 20337.92 | F54: =IFERROR('DATA SHEET'!E64,0) -> 20812.75 | G54: =IFERROR('DATA SHEET'!F64,0) -> 15770.72 | H54: =IFERROR('DATA SHEET'!G64,0) -> 16308.48 | I54: =IFERROR('DATA SHEET'!H64,0) -> 24620.28 | J54: =IFERROR('DATA SHEET'!I64,0) -> 29379.53 | ... L54: =IFERROR('DATA SHEET'!K64,0) -> 22971.07
B55: Other Assets | C55: ='DATA SHEET'!B65-SUM('DATA SHEET'!B67:B69) -> 30891.17 | D55: ='DATA SHEET'!C65-SUM('DATA SHEET'!C67:C69) -> 29579.36 | E55: ='DATA SHEET'!D65-SUM('DATA SHEET'!D67:D69) -> 37360.78 | F55: ='DATA SHEET'!E65-SUM('DATA SHEET'!E67:E69) -> 48286.86 | G55: ='DATA SHEET'!F65-SUM('DATA SHEET'!F67:F69) -> 56155.74 | H55: ='DATA SHEET'!G65-SUM('DATA SHEET'!G67:G69) -> 58784.94 | I55: ='DATA SHEET'!H65-SUM('DATA SHEET'!H67:H69) -> 61717.96 | J55: ='DATA SHEET'!I65-SUM('DATA SHEET'!I67:I69) -> 62223.77 | ... L55: ='DATA SHEET'!K65-SUM('DATA SHEET'!K67:K69) -> 79018.86
B56: Total Non Current Assets | C56: =SUM(C52:C55) -> 163347.49 | D56: =SUM(D52:D55) -> 186497.08 | E56: =SUM(E52:E55) -> 187341.62 | F56: =SUM(F52:F55) -> 230546.97 | G56: =SUM(G52:G55) -> 215044.77 | H56: =SUM(H52:H55) -> 237822.85 | I56: =SUM(I52:I55) -> 246009.78 | J56: =SUM(J52:J55) -> 240709.84 | ... L56: =SUM(L52:L55) -> 258973.82
B58: Receivables | C58: =IFERROR('DATA SHEET'!B67,0) -> 12579.2 | D58: =IFERROR('DATA SHEET'!C67,0) -> 13570.91 | E58: =IFERROR('DATA SHEET'!D67,0) -> 14075.55 | F58: =IFERROR('DATA SHEET'!E67,0) -> 19893.3 | G58: =IFERROR('DATA SHEET'!F67,0) -> 18996.17 | H58: =IFERROR('DATA SHEET'!G67,0) -> 11172.69 | I58: =IFERROR('DATA SHEET'!H67,0) -> 12679.08 | J58: =IFERROR('DATA SHEET'!I67,0) -> 12442.12 | ... L58: =IFERROR('DATA SHEET'!K67,0) -> 16951.81
B59: Inventory | C59: =IFERROR('DATA SHEET'!B68,0) -> 29272.34 | D59: =IFERROR('DATA SHEET'!C68,0) -> 32655.73 | E59: =IFERROR('DATA SHEET'!D68,0) -> 35085.31 | F59: =IFERROR('DATA SHEET'!E68,0) -> 42137.63 | G59: =IFERROR('DATA SHEET'!F68,0) -> 39013.73 | H59: =IFERROR('DATA SHEET'!G68,0) -> 37456.88 | I59: =IFERROR('DATA SHEET'!H68,0) -> 36088.59 | J59: =IFERROR('DATA SHEET'!I68,0) -> 35240.34 | ... L59: =IFERROR('DATA SHEET'!K68,0) -> 47788.29
B60: Cash & Bank | C60: =IFERROR('DATA SHEET'!B69,0) -> 32115.76 | D60: =IFERROR('DATA SHEET'!C69,0) -> 30460.4 | E60: =IFERROR('DATA SHEET'!D69,0) -> 36077.88 | F60: =IFERROR('DATA SHEET'!E69,0) -> 34613.91 | G60: =IFERROR('DATA SHEET'!F69,0) -> 32648.82 | H60: =IFERROR('DATA SHEET'!G69,0) -> 33726.97 | I60: =IFERROR('DATA SHEET'!H69,0) -> 46792.46 | J60: =IFERROR('DATA SHEET'!I69,0) -> 40669.19 | ... L60: =IFERROR('DATA SHEET'!K69,0) -> 45806.69
B61: Total Current Assets | C61: =SUM(C58:C60) -> 73967.3 | D61: =SUM(D58:D60) -> 76687.04 | E61: =SUM(E58:E60) -> 85238.74 | F61: =SUM(F58:F60) -> 96644.84 | G61: =SUM(G58:G60) -> 90658.72 | H61: =SUM(H58:H60) -> 82356.54 | I61: =SUM(I58:I60) -> 95560.13 | J61: =SUM(J58:J60) -> 88351.65 | ... L61: =SUM(L58:L60) -> 110546.79
B63: Total Assets | C63: =SUM(C56,C61) -> 237314.79 | D63: =SUM(D56,D61) -> 263184.12 | E63: =SUM(E56,E61) -> 272580.36 | F63: =SUM(F56,F61) -> 327191.81 | G63: =SUM(G56,G61) -> 305703.49 | H63: =SUM(H56,H61) -> 320179.39 | I63: =SUM(I56,I61) -> 341569.91 | J63: =SUM(J56,J61) -> 329061.49 | ... L63: =SUM(L56,L61) -> 369520.61
B65: CHECK | C65: =C63=C50 -> TRUE | D65: =D63=D50 -> TRUE | E65: =E63=E50 -> TRUE | F65: =F63=F50 -> TRUE | G65: =G63=G50 -> TRUE | H65: =H63=H50 -> TRUE | I65: =I63=I50 -> TRUE | J65: =J63=J50 -> TRUE | ... L65: =L63=L50 -> TRUE
A68: # | B68: CASH FLOW STATEMENT
B69: Operating Activities
B70: Profit from operations | C70: =IFERROR('CASH FLOW DATA'!E4,0) -> 43397 | D70: =IFERROR('CASH FLOW DATA'!F4,0) -> 38626 | E70: =IFERROR('CASH FLOW DATA'!G4,0) -> 28840 | F70: =IFERROR('CASH FLOW DATA'!H4,0) -> 33312 | G70: =IFERROR('CASH FLOW DATA'!I4,0) -> 28771 | H70: =IFERROR('CASH FLOW DATA'!J4,0) -> 23352 | I70: =IFERROR('CASH FLOW DATA'!K4,0) -> 31198 | J70: =IFERROR('CASH FLOW DATA'!L4,0) -> 26943 | ... L70: =IFERROR('CASH FLOW DATA'!N4,0) -> 65106
B71: Receivables | C71: =IFERROR('CASH FLOW DATA'!E5,0) -> -3179 | D71: =IFERROR('CASH FLOW DATA'!F5,0) -> -2223 | E71: =IFERROR('CASH FLOW DATA'!G5,0) -> -4152 | F71: =IFERROR('CASH FLOW DATA'!H5,0) -> -10688 | G71: =IFERROR('CASH FLOW DATA'!I5,0) -> -9109 | H71: =IFERROR('CASH FLOW DATA'!J5,0) -> 9950 | I71: =IFERROR('CASH FLOW DATA'!K5,0) -> -5505 | J71: =IFERROR('CASH FLOW DATA'!L5,0) -> 185 | ... L71: =IFERROR('CASH FLOW DATA'!N5,0) -> -1875
B72: Inventory | C72: =IFERROR('CASH FLOW DATA'!E6,0) -> -3692 | D72: =IFERROR('CASH FLOW DATA'!F6,0) -> -5743 | E72: =IFERROR('CASH FLOW DATA'!G6,0) -> -6621 | F72: =IFERROR('CASH FLOW DATA'!H6,0) -> -3560 | G72: =IFERROR('CASH FLOW DATA'!I6,0) -> 2069 | H72: =IFERROR('CASH FLOW DATA'!J6,0) -> 2326 | I72: =IFERROR('CASH FLOW DATA'!K6,0) -> 3814 | J72: =IFERROR('CASH FLOW DATA'!L6,0) -> 472 | ... L72: =IFERROR('CASH FLOW DATA'!N6,0) -> -7265
B73: Payables | C73: =IFERROR('CASH FLOW DATA'!E7,0) -> 3598 | D73: =IFERROR('CASH FLOW DATA'!F7,0) -> 3947 | E73: =IFERROR('CASH FLOW DATA'!G7,0) -> 9301 | F73: =IFERROR('CASH FLOW DATA'!H7,0) -> 7320 | G73: =IFERROR('CASH FLOW DATA'!I7,0) -> -4692 | H73: =IFERROR('CASH FLOW DATA'!J7,0) -> -8085 | I73: =IFERROR('CASH FLOW DATA'!K7,0) -> 5748 | J73: =IFERROR('CASH FLOW DATA'!L7,0) -> -7012 | ... L73: =IFERROR('CASH FLOW DATA'!N7,0) -> 13706
B74: Loans Advances | C74: =IFERROR('CASH FLOW DATA'!E8,0) -> 0 | D74: =IFERROR('CASH FLOW DATA'!F8,0) -> -520 | E74: =IFERROR('CASH FLOW DATA'!G8,0) -> 0 | F74: =IFERROR('CASH FLOW DATA'!H8,0) -> 0 | G74: =IFERROR('CASH FLOW DATA'!I8,0) -> 0 | H74: =IFERROR('CASH FLOW DATA'!J8,0) -> 0 | I74: =IFERROR('CASH FLOW DATA'!K8,0) -> 0 | J74: =IFERROR('CASH FLOW DATA'!L8,0) -> 0 | ... L74: =IFERROR('CASH FLOW DATA'!N8,0) -> 0
B75: Other WC items | C75: =IFERROR('CASH FLOW DATA'!E9,0) -> -398 | D75: =IFERROR('CASH FLOW DATA'!F9,0) -> 5852 | E75: =IFERROR('CASH FLOW DATA'!G9,0) -> 4727 | F75: =IFERROR('CASH FLOW DATA'!H9,0) -> 494 | G75: =IFERROR('CASH FLOW DATA'!I9,0) -> 4512 | H75: =IFERROR('CASH FLOW DATA'!J9,0) -> 875 | I75: =IFERROR('CASH FLOW DATA'!K9,0) -> -4150 | J75: =IFERROR('CASH FLOW DATA'!L9,0) -> -4396 | ... L75: =IFERROR('CASH FLOW DATA'!N9,0) -> 2760
B76: Working capital changes | C76: =IFERROR('CASH FLOW DATA'!E10,0) -> -3672 | D76: =IFERROR('CASH FLOW DATA'!F10,0) -> 1313 | E76: =IFERROR('CASH FLOW DATA'!G10,0) -> 3254 | F76: =IFERROR('CASH FLOW DATA'!H10,0) -> -6434 | G76: =IFERROR('CASH FLOW DATA'!I10,0) -> -7221 | H76: =IFERROR('CASH FLOW DATA'!J10,0) -> 5065 | I76: =IFERROR('CASH FLOW DATA'!K10,0) -> -93 | J76: =IFERROR('CASH FLOW DATA'!L10,0) -> -10750 | ... L76: =IFERROR('CASH FLOW DATA'!N10,0) -> 7325
B77: Direct taxes | C77: =IFERROR('CASH FLOW DATA'!E11,0) -> -4194 | D77: =IFERROR('CASH FLOW DATA'!F11,0) -> -2040 | E77: =IFERROR('CASH FLOW DATA'!G11,0) -> -1895 | F77: =IFERROR('CASH FLOW DATA'!H11,0) -> -3021 | G77: =IFERROR('CASH FLOW DATA'!I11,0) -> -2659 | H77: =IFERROR('CASH FLOW DATA'!J11,0) -> -1785 | I77: =IFERROR('CASH FLOW DATA'!K11,0) -> -2105 | J77: =IFERROR('CASH FLOW DATA'!L11,0) -> -1910 | ... L77: =IFERROR('CASH FLOW DATA'!N11,0) -> -4516
B78: Cash From Operating Activities | C78: =SUM(C70:C75)+C77 -> 35532 | D78: =SUM(D70:D75)+D77 -> 37899 | E78: =SUM(E70:E75)+E77 -> 30200 | F78: =SUM(F70:F75)+F77 -> 23857 | G78: =SUM(G70:G75)+G77 -> 18892 | H78: =SUM(H70:H75)+H77 -> 26633 | I78: =SUM(I70:I75)+I77 -> 29000 | J78: =SUM(J70:J75)+J77 -> 14282 | ... L78: =SUM(L70:L75)+L77 -> 67916
B81: Investing Activities
B82: Fixed assets purchased | C82: =IFERROR('CASH FLOW DATA'!E13,0) -> -31962 | D82: =IFERROR('CASH FLOW DATA'!F13,0) -> -31503 | E82: =IFERROR('CASH FLOW DATA'!G13,0) -> -16072 | F82: =IFERROR('CASH FLOW DATA'!H13,0) -> -35079 | G82: =IFERROR('CASH FLOW DATA'!I13,0) -> -35304 | H82: =IFERROR('CASH FLOW DATA'!J13,0) -> -29702 | I82: =IFERROR('CASH FLOW DATA'!K13,0) -> -20205 | J82: =IFERROR('CASH FLOW DATA'!L13,0) -> -15168 | ... L82: =IFERROR('CASH FLOW DATA'!N13,0) -> -31414
B83: Fixed assets sold | C83: =IFERROR('CASH FLOW DATA'!E14,0) -> 74 | D83: =IFERROR('CASH FLOW DATA'!F14,0) -> 59 | E83: =IFERROR('CASH FLOW DATA'!G14,0) -> 53 | F83: =IFERROR('CASH FLOW DATA'!H14,0) -> 30 | G83: =IFERROR('CASH FLOW DATA'!I14,0) -> 67 | H83: =IFERROR('CASH FLOW DATA'!J14,0) -> 171 | I83: =IFERROR('CASH FLOW DATA'!K14,0) -> 351 | J83: =IFERROR('CASH FLOW DATA'!L14,0) -> 230 | ... L83: =IFERROR('CASH FLOW DATA'!N14,0) -> 231
B84: Investments purchased | C84: =IFERROR('CASH FLOW DATA'!E15,0) -> -5461 | D84: =IFERROR('CASH FLOW DATA'!F15,0) -> -4728 | E84: =IFERROR('CASH FLOW DATA'!G15,0) -> -6 | F84: =IFERROR('CASH FLOW DATA'!H15,0) -> -329 | G84: =IFERROR('CASH FLOW DATA'!I15,0) -> -130 | H84: =IFERROR('CASH FLOW DATA'!J15,0) -> -1439 | I84: =IFERROR('CASH FLOW DATA'!K15,0) -> -7530 | J84: =IFERROR('CASH FLOW DATA'!L15,0) -> -3008 | ... L84: =IFERROR('CASH FLOW DATA'!N15,0) -> -74
B85: Investments sold | C85: =IFERROR('CASH FLOW DATA'!E16,0) -> 42 | D85: =IFERROR('CASH FLOW DATA'!F16,0) -> 89 | E85: =IFERROR('CASH FLOW DATA'!G16,0) -> 1965 | F85: =IFERROR('CASH FLOW DATA'!H16,0) -> 2381 | G85: =IFERROR('CASH FLOW DATA'!I16,0) -> 5644 | H85: =IFERROR('CASH FLOW DATA'!J16,0) -> 21 | I85: =IFERROR('CASH FLOW DATA'!K16,0) -> 226 | J85: =IFERROR('CASH FLOW DATA'!L16,0) -> 104 | ... L85: =IFERROR('CASH FLOW DATA'!N16,0) -> 10820
B86: Interest received | C86: =IFERROR('CASH FLOW DATA'!E17,0) -> 698 | D86: =IFERROR('CASH FLOW DATA'!F17,0) -> 731 | E86: =IFERROR('CASH FLOW DATA'!G17,0) -> 638 | F86: =IFERROR('CASH FLOW DATA'!H17,0) -> 690 | G86: =IFERROR('CASH FLOW DATA'!I17,0) -> 761 | H86: =IFERROR('CASH FLOW DATA'!J17,0) -> 1104 | I86: =IFERROR('CASH FLOW DATA'!K17,0) -> 428 | J86: =IFERROR('CASH FLOW DATA'!L17,0) -> 653 | ... L86: =IFERROR('CASH FLOW DATA'!N17,0) -> 2493
B87: Dividends received | C87: =IFERROR('CASH FLOW DATA'!E18,0) -> 80 | D87: =IFERROR('CASH FLOW DATA'!F18,0) -> 58 | E87: =IFERROR('CASH FLOW DATA'!G18,0) -> 620 | F87: =IFERROR('CASH FLOW DATA'!H18,0) -> 1797 | G87: =IFERROR('CASH FLOW DATA'!I18,0) -> 232 | H87: =IFERROR('CASH FLOW DATA'!J18,0) -> 21 | I87: =IFERROR('CASH FLOW DATA'!K18,0) -> 18 | J87: =IFERROR('CASH FLOW DATA'!L18,0) -> 32 | ... L87: =IFERROR('CASH FLOW DATA'!N18,0) -> 47
B88: Investment in group cos | C88: =IFERROR('CASH FLOW DATA'!E19,0) -> -160 | D88: =IFERROR('CASH FLOW DATA'!F19,0) -> 0 | E88: =IFERROR('CASH FLOW DATA'!G19,0) -> -107 | F88: =IFERROR('CASH FLOW DATA'!H19,0) -> -4 | G88: =IFERROR('CASH FLOW DATA'!I19,0) -> -9 | H88: =IFERROR('CASH FLOW DATA'!J19,0) -> -606 | I88: =IFERROR('CASH FLOW DATA'!K19,0) -> -10 | J88: =IFERROR('CASH FLOW DATA'!L19,0) -> 0 | ... L88: =IFERROR('CASH FLOW DATA'!N19,0) -> -150
B89: Redemp n Canc of Shares | C89: =IFERROR('CASH FLOW DATA'!E20,0) -> 0 | D89: =IFERROR('CASH FLOW DATA'!F20,0) -> 0 | E89: =IFERROR('CASH FLOW DATA'!G20,0) -> 0 | F89: =IFERROR('CASH FLOW DATA'!H20,0) -> 14 | G89: =IFERROR('CASH FLOW DATA'!I20,0) -> 533 | H89: =IFERROR('CASH FLOW DATA'!J20,0) -> 0 | I89: =IFERROR('CASH FLOW DATA'!K20,0) -> 0 | J89: =IFERROR('CASH FLOW DATA'!L20,0) -> 0 | ... L89: =IFERROR('CASH FLOW DATA'!N20,0) -> 108
B90: Acquisition of companies | C90: =IFERROR('CASH FLOW DATA'!E21,0) -> 0 | D90: =IFERROR('CASH FLOW DATA'!F21,0) -> -111 | E90: =IFERROR('CASH FLOW DATA'!G21,0) -> 0 | F90: =IFERROR('CASH FLOW DATA'!H21,0) -> 0 | G90: =IFERROR('CASH FLOW DATA'!I21,0) -> -8 | H90: =IFERROR('CASH FLOW DATA'!J21,0) -> -27 | I90: =IFERROR('CASH FLOW DATA'!K21,0) -> 0 | J90: =IFERROR('CASH FLOW DATA'!L21,0) -> -98 | ... L90: =IFERROR('CASH FLOW DATA'!N21,0) -> 0
B91: Inter corporate deposits | C91: =IFERROR('CASH FLOW DATA'!E22,0) -> 0 | D91: =IFERROR('CASH FLOW DATA'!F22,0) -> 0 | E91: =IFERROR('CASH FLOW DATA'!G22,0) -> 0 | F91: =IFERROR('CASH FLOW DATA'!H22,0) -> 0 | G91: =IFERROR('CASH FLOW DATA'!I22,0) -> 0 | H91: =IFERROR('CASH FLOW DATA'!J22,0) -> 0 | I91: =IFERROR('CASH FLOW DATA'!K22,0) -> 0 | J91: =IFERROR('CASH FLOW DATA'!L22,0) -> 0 | ... L91: =IFERROR('CASH FLOW DATA'!N22,0) -> -24
B92: Other investing items | C92: =IFERROR('CASH FLOW DATA'!E23,0) -> 456 | D92: =IFERROR('CASH FLOW DATA'!F23,0) -> -1289 | E92: =IFERROR('CASH FLOW DATA'!G23,0) -> -26663 | F92: =IFERROR('CASH FLOW DATA'!H23,0) -> 5360 | G92: =IFERROR('CASH FLOW DATA'!I23,0) -> 7335 | H92: =IFERROR('CASH FLOW DATA'!J23,0) -> -2659 | I92: =IFERROR('CASH FLOW DATA'!K23,0) -> 1051 | J92: =IFERROR('CASH FLOW DATA'!L23,0) -> 12813 | ... L92: =IFERROR('CASH FLOW DATA'!N23,0) -> -4817
B93: Cash From Investing Activities | C93: =SUM(C82:C92) -> -36233 | D93: =SUM(D82:D92) -> -36694 | E93: =SUM(E82:E92) -> -39572 | F93: =SUM(F82:F92) -> -25140 | G93: =SUM(G82:G92) -> -20879 | H93: =SUM(H82:H92) -> -33116 | I93: =SUM(I82:I92) -> -25671 | J93: =SUM(J82:J92) -> -4442 | ... L93: =SUM(L82:L92) -> -22780
B96: Financing Activities
B97: Proceeds from shares | C97: =IFERROR('CASH FLOW DATA'!E25,0) -> 0 | D97: =IFERROR('CASH FLOW DATA'!F25,0) -> 7433 | E97: =IFERROR('CASH FLOW DATA'!G25,0) -> 5 | F97: =IFERROR('CASH FLOW DATA'!H25,0) -> 0 | G97: =IFERROR('CASH FLOW DATA'!I25,0) -> 0 | H97: =IFERROR('CASH FLOW DATA'!J25,0) -> 3889 | I97: =IFERROR('CASH FLOW DATA'!K25,0) -> 2603 | J97: =IFERROR('CASH FLOW DATA'!L25,0) -> 19 | ... L97: =IFERROR('CASH FLOW DATA'!N25,0) -> 82
B98: Redemption of debentures | C98: =IFERROR('CASH FLOW DATA'!E26,0) -> -744 | D98: =IFERROR('CASH FLOW DATA'!F26,0) -> 0 | E98: =IFERROR('CASH FLOW DATA'!G26,0) -> 0 | F98: =IFERROR('CASH FLOW DATA'!H26,0) -> 0 | G98: =IFERROR('CASH FLOW DATA'!I26,0) -> 0 | H98: =IFERROR('CASH FLOW DATA'!J26,0) -> 0 | I98: =IFERROR('CASH FLOW DATA'!K26,0) -> 0 | J98: =IFERROR('CASH FLOW DATA'!L26,0) -> 0 | ... L98: =IFERROR('CASH FLOW DATA'!N26,0) -> 0
B99: Proceeds from borrowings | C99: =IFERROR('CASH FLOW DATA'!E27,0) -> 36363 | D99: =IFERROR('CASH FLOW DATA'!F27,0) -> 19519 | E99: =IFERROR('CASH FLOW DATA'!G27,0) -> 33390 | F99: =IFERROR('CASH FLOW DATA'!H27,0) -> 37482 | G99: =IFERROR('CASH FLOW DATA'!I27,0) -> 51128 | H99: =IFERROR('CASH FLOW DATA'!J27,0) -> 38297 | I99: =IFERROR('CASH FLOW DATA'!K27,0) -> 46641 | J99: =IFERROR('CASH FLOW DATA'!L27,0) -> 46578 | ... L99: =IFERROR('CASH FLOW DATA'!N27,0) -> 18747
B100: Repayment of borrowings | C100: =IFERROR('CASH FLOW DATA'!E28,0) -> -23332 | D100: =IFERROR('CASH FLOW DATA'!F28,0) -> -24924 | E100: =IFERROR('CASH FLOW DATA'!G28,0) -> -21732 | F100: =IFERROR('CASH FLOW DATA'!H28,0) -> -29964 | G100: =IFERROR('CASH FLOW DATA'!I28,0) -> -35198 | H100: =IFERROR('CASH FLOW DATA'!J28,0) -> -29847 | I100: =IFERROR('CASH FLOW DATA'!K28,0) -> -29709 | J100: =IFERROR('CASH FLOW DATA'!L28,0) -> -42816 | ... L100: =IFERROR('CASH FLOW DATA'!N28,0) -> -47332
B101: Interest paid fin | C101: =IFERROR('CASH FLOW DATA'!E29,0) -> -6307 | D101: =IFERROR('CASH FLOW DATA'!F29,0) -> -5716 | E101: =IFERROR('CASH FLOW DATA'!G29,0) -> -5336 | F101: =IFERROR('CASH FLOW DATA'!H29,0) -> -5411 | G101: =IFERROR('CASH FLOW DATA'!I29,0) -> -7005 | H101: =IFERROR('CASH FLOW DATA'!J29,0) -> -7518 | I101: =IFERROR('CASH FLOW DATA'!K29,0) -> -8123 | J101: =IFERROR('CASH FLOW DATA'!L29,0) -> -9251 | ... L101: =IFERROR('CASH FLOW DATA'!N29,0) -> -9332
B102: Dividends paid | C102: =IFERROR('CASH FLOW DATA'!E30,0) -> -720 | D102: =IFERROR('CASH FLOW DATA'!F30,0) -> -108 | E102: =IFERROR('CASH FLOW DATA'!G30,0) -> -121 | F102: =IFERROR('CASH FLOW DATA'!H30,0) -> -96 | G102: =IFERROR('CASH FLOW DATA'!I30,0) -> -95 | H102: =IFERROR('CASH FLOW DATA'!J30,0) -> -57 | I102: =IFERROR('CASH FLOW DATA'!K30,0) -> -30 | J102: =IFERROR('CASH FLOW DATA'!L30,0) -> -100 | ... L102: =IFERROR('CASH FLOW DATA'!N30,0) -> -1059
B103: Financial liabilities | C103: =IFERROR('CASH FLOW DATA'!E31,0) -> 0 | D103: =IFERROR('CASH FLOW DATA'!F31,0) -> 0 | E103: =IFERROR('CASH FLOW DATA'!G31,0) -> 0 | F103: =IFERROR('CASH FLOW DATA'!H31,0) -> 0 | G103: =IFERROR('CASH FLOW DATA'!I31,0) -> 0 | H103: =IFERROR('CASH FLOW DATA'!J31,0) -> -1346 | I103: =IFERROR('CASH FLOW DATA'!K31,0) -> -1477 | J103: =IFERROR('CASH FLOW DATA'!L31,0) -> -1559 | ... L103: =IFERROR('CASH FLOW DATA'!N31,0) -> -1924
B104: Other financing items | C104: =IFERROR('CASH FLOW DATA'!E32,0) -> -57 | D104: =IFERROR('CASH FLOW DATA'!F32,0) -> 0 | E104: =IFERROR('CASH FLOW DATA'!G32,0) -> 0 | F104: =IFERROR('CASH FLOW DATA'!H32,0) -> 0 | G104: =IFERROR('CASH FLOW DATA'!I32,0) -> 0 | H104: =IFERROR('CASH FLOW DATA'!J32,0) -> -29 | I104: =IFERROR('CASH FLOW DATA'!K32,0) -> 0 | J104: =IFERROR('CASH FLOW DATA'!L32,0) -> 3750 | ... L104: =IFERROR('CASH FLOW DATA'!N32,0) -> 3812
B105: Cash From Financing Activities | C105: =SUM(C97:C104) -> 5203 | D105: =SUM(D97:D104) -> -3796 | E105: =SUM(E97:E104) -> 6206 | F105: =SUM(F97:F104) -> 2011 | G105: =SUM(G97:G104) -> 8830 | H105: =SUM(H97:H104) -> 3389 | I105: =SUM(I97:I104) -> 9905 | J105: =SUM(J97:J104) -> -3379 | ... L105: =SUM(L97:L104) -> -37006
B107: Net Cash Flow | C107: =SUM(C78,C93,C105) -> 4502 | D107: =SUM(D78,D93,D105) -> -2591 | E107: =SUM(E78,E93,E105) -> -3166 | F107: =SUM(F78,F93,F105) -> 728 | G107: =SUM(G78,G93,G105) -> 6843 | H107: =SUM(H78,H93,H105) -> -3094 | I107: =SUM(I78,I93,I105) -> 13234 | J107: =SUM(J78,J93,J105) -> 6461 | ... L107: =SUM(L78,L93,L105) -> 8130

Sheet CASH FLOW DATA
C2: 41334 | D2: 41699 | E2: 42064 | F2: 42430 | G2: 42795 | H2: 43160 | I2: 43525 | J2: 43891 | K2: 44256 | L2: 44621 | M2: 44986 | N2: 45352
B3: Cash from Operating Activity - | C3: 22163 | D3: 36151 | E3: 35531 | F3: 37900 | G3: 30199 | H3: 23857 | I3: 18891 | J3: 26633 | K3: 29001 | L3: 14283 | M3: 35388 | N3: 67915
B4: Profit from operations | C4: 24406 | D4: 36303 | E4: 43397 | F4: 38626 | G4: 28840 | H4: 33312 | I4: 28771 | J4: 23352 | K4: 31198 | L4: 26943 | M4: 41694 | N4: 65106
B5: Receivables | C5: -5177 | D5: 445 | E5: -3179 | F5: -2223 | G5: -4152 | H5: -10688 | I5: -9109 | J5: 9950 | K5: -5505 | L5: 185 | M5: -2213 | N5: -1875
B6: Inventory | C6: -2656 | D6: -2853 | E6: -3692 | F6: -5743 | G6: -6621 | H6: -3560 | I6: 2069 | J6: 2326 | K6: 3814 | L6: 472 | M6: -5665 | N6: -7265
B7: Payables | C7: 8132 | D7: 4694 | E7: 3598 | F7: 3947 | G7: 9301 | H7: 7320 | I7: -4692 | J7: -8085 | K7: 5748 | L7: -7012 | M7: 6945 | N7: 13706
B8: Loans Advances | C8: 0 | D8: 0 | E8: 0 | F8: -520 | G8: 0 | H8: 0 | I8: 0 | J8: 0 | K8: 0 | L8: 0 | M8: 0 | N8: 0
B9: Other WC items | C9: -303 | D9: 1870 | E9: -398 | F9: 5852 | G9: 4727 | H9: 494 | I9: 4512 | J9: 875 | K9: -4150 | L9: -4396 | M9: -2194 | N9: 2760
B10: Working capital changes | C10: -3 | D10: 4157 | E10: -3672 | F10: 1313 | G10: 3254 | H10: -6434 | I10: -7221 | J10: 5065 | K10: -93 | L10: -10750 | M10: -3127 | N10: 7325
B11: Direct taxes | C11: -2240 | D11: -4308 | E11: -4194 | F11: -2040 | G11: -1895 | H11: -3021 | I11: -2659 | J11: -1785 | K11: -2105 | L11: -1910 | M11: -3179 | N11: -4516
B12: Cash from Investing Activity - | C12: -22969 | D12: -27991 | E12: -36232 | F12: -36694 | G12: -39571 | H12: -25139 | I12: -20878 | J12: -33115 | K12: -25672 | L12: -4444 | M12: -15417 | N12: -22782
B13: Fixed assets purchased | C13: -18863 | D13: -26975 | E13: -31962 | F13: -31503 | G13: -16072 | H13: -35079 | I13: -35304 | J13: -29702 | K13: -20205 | L13: -15168 | M13: -19230 | N13: -31414
B14: Fixed assets sold | C14: 37 | D14: 50 | E14: 74 | F14: 59 | G14: 53 | H14: 30 | I14: 67 | J14: 171 | K14: 351 | L14: 230 | M14: 285 | N14: 231
... B33: Net Cash Flow | C33: -2499 | D33: 4277 | E33: 4500 | F33: -2589 | G33: -3167 | H33: 730 | I33: 6843 | J33: -3092 | K33: 13232 | L33: 6459 | M33: -6272 | N33: 8128

Sheet RATIO ANALYSIS 
B1: Ratio Analysis-TATA MOTORS LTD
B2: Years | C2: 42094 | D2: 42460 | E2: 42825 | F2: 43190 | G2: 43555 | H2: 43921 | I2: 44286 | J2: 44651 | K2: 45016 | L2: 45382 | N2: Mean | O2: Median
B3: Sales Growth | C3: 263158.98 | D3: 273045.6 | E3: 269692.51 | F3: 291550.48 | G3: 301938.4 | H3: 261067.97 | I3: 249794.75 | J3: 278453.62 | K3: 345966.97 | L3: 437927.77
B4: Sales Growth | D4: =IFERROR('HISTORICAL FS'!D6,0) -> 0.037569001 | E4: =IFERROR('HISTORICAL FS'!E6,0) -> -0.01228033 | F4: =IFERROR('HISTORICAL FS'!F6,0) -> 0.081047746 | G4: =IFERROR('HISTORICAL FS'!G6,0) -> 0.035629919 | H4: =IFERROR('HISTORICAL FS'!H6,0) -> -0.13536016 | I4: =IFERROR('HISTORICAL FS'!I6,0) -> -0.043181168 | J4: =IFERROR('HISTORICAL FS'!J6,0) -> 0.11472967 | K4: =IFERROR('HISTORICAL FS'!K6,0) -> 0.24245815 | L4: =IFERROR('HISTORICAL FS'!L6,0) -> 0.26580803 | N4: =IFERROR(AVERAGE(D4:L4),0) -> 0.065157874 | O4: =IFERROR(MEDIAN(D4:L4),0) -> 0.037569001
B5: EBITDA Growth | D5: =IFERROR('HISTORICAL FS'!D17/'HISTORICAL FS'!C17-1,0) -> -0.021494114 | E5: =IFERROR('HISTORICAL FS'!E17/'HISTORICAL FS'!D17-1,0) -> -0.22936587 | F5: =IFERROR('HISTORICAL FS'!F17/'HISTORICAL FS'!E17-1,0) -> 0.063165689 | G5: =IFERROR('HISTORICAL FS'!G17/'HISTORICAL FS'!F17-1,0) -> -0.21595203 | H5: =IFERROR('HISTORICAL FS'!H17/'HISTORICAL FS'!G17-1,0) -> -0.27072538 | I5: =IFERROR('HISTORICAL FS'!I17/'HISTORICAL FS'!H17-1,0) -> 0.79503554 | J5: =IFERROR('HISTORICAL FS'!J17/'HISTORICAL FS'!I17-1,0) -> -0.23437418 | K5: =IFERROR('HISTORICAL FS'!K17/'HISTORICAL FS'!J17-1,0) -> 0.28704224 | L5: =IFERROR('HISTORICAL FS'!L17/'HISTORICAL FS'!K17-1,0) -> 0.87134505 | N5: =IFERROR(AVERAGE(D5:L5),0) -> 0.11607522 | O5: =IFERROR(MEDIAN(D5:L5),0) -> -0.021494114
B6: EBIT Growth | D6: =IFERROR('HISTORICAL FS'!D26/'HISTORICAL FS'!C26-1,0) -> -0.34911964 | E6: =IFERROR('HISTORICAL FS'!E26/'HISTORICAL FS'!D26-1,0) -> -0.34058179 | F6: =IFERROR('HISTORICAL FS'!F26/'HISTORICAL FS'!E26-1,0) -> 0.19756108 | G6: =IFERROR('HISTORICAL FS'!G26/'HISTORICAL FS'!F26-1,0) -> -3.8122874 | H6: =IFERROR('HISTORICAL FS'!H26/'HISTORICAL FS'!G26-1,0) -> -0.6627481 | I6: =IFERROR('HISTORICAL FS'!I26/'HISTORICAL FS'!H26-1,0) -> -0.0099905671 | J6: =IFERROR('HISTORICAL FS'!J26/'HISTORICAL FS'!I26-1,0) -> -0.33137075 | K6: =IFERROR('HISTORICAL FS'!K26/'HISTORICAL FS'!J26-1,0) -> -1.4846111 | L6: =IFERROR('HISTORICAL FS'!L26/'HISTORICAL FS'!K26-1,0) -> 7.2367963 | N6: =IFERROR(AVERAGE(D6:L6),0) -> 0.049294231 | O6: =IFERROR(MEDIAN(D6:L6),0) -> -0.34058179
B7: Net Profit Growth | D7: =IFERROR('HISTORICAL FS'!D32/'HISTORICAL FS'!C32-1,0) -> -0.21045545 | E7: =IFERROR('HISTORICAL FS'!E32/'HISTORICAL FS'!D32-1,0) -> -0.45376876 | F7: =IFERROR('HISTORICAL FS'!F32/'HISTORICAL FS'!E32-1,0) -> 0.12361385 | G7: =IFERROR('HISTORICAL FS'!G32/'HISTORICAL FS'!F32-1,0) -> -5.2467746 | H7: =IFERROR('HISTORICAL FS'!H32/'HISTORICAL FS'!G32-1,0) -> -0.62067658 | I7: =IFERROR('HISTORICAL FS'!I32/'HISTORICAL FS'!H32-1,0) -> 0.18595601 | J7: =IFERROR('HISTORICAL FS'!J32/'HISTORICAL FS'!I32-1,0) -> -0.13686392 | K7: =IFERROR('HISTORICAL FS'!K32/'HISTORICAL FS'!J32-1,0) -> -1.2394252 | L7: =IFERROR('HISTORICAL FS'!L32/'HISTORICAL FS'!K32-1,0) -> 10.824642 | N7: =IFERROR(AVERAGE(D7:L7),0) -> 0.35847194 | O7: =IFERROR(MEDIAN(D7:L7),0) -> -0.21045545
B8: Dividend Growth | D8: =IFERROR('HISTORICAL FS'!D39/'HISTORICAL FS'!C39-1,0) -> 0 | E8: =IFERROR('HISTORICAL FS'!E39/'HISTORICAL FS'!D39-1,0) -> -1 | F8: =IFERROR('HISTORICAL FS'!F39/'HISTORICAL FS'!E39-1,0) -> 0 | G8: =IFERROR('HISTORICAL FS'!G39/'HISTORICAL FS'!F39-1,0) -> 0 | H8: =IFERROR('HISTORICAL FS'!H39/'HISTORICAL FS'!G39-1,0) -> 0 | I8: =IFERROR('HISTORICAL FS'!I39/'HISTORICAL FS'!H39-1,0) -> 0 | J8: =IFERROR('HISTORICAL FS'!J39/'HISTORICAL FS'!I39-1,0) -> 0 | K8: =IFERROR('HISTORICAL FS'!K39/'HISTORICAL FS'!J39-1,0) -> 0 | L8: =IFERROR('HISTORICAL FS'!L39/'HISTORICAL FS'!K39-1,0) -> 1.9997122 | N8: =IFERROR(AVERAGE(D8:L8),0) -> 0.11107914 | O8: =IFERROR(MEDIAN(D8:L8),0) -> 0
B10: Gross Margin | C10: =IFERROR('HISTORICAL FS'!C11/'HISTORICAL FS'!C5,0) -> 0.22914703 | D10: =IFERROR('HISTORICAL FS'!D11/'HISTORICAL FS'!D5,0) -> 0.24734524 | E10: =IFERROR('HISTORICAL FS'!E11/'HISTORICAL FS'!E5,0) -> 0.23819078 | F10: =IFERROR('HISTORICAL FS'!F11/'HISTORICAL FS'!F5,0) -> 0.2164999 | G10: =IFERROR('HISTORICAL FS'!G11/'HISTORICAL FS'!G5,0) -> 0.19571167 | H10: =IFERROR('HISTORICAL FS'!H11/'HISTORICAL FS'!H5,0) -> 0.19417127 | I10: =IFERROR('HISTORICAL FS'!I11/'HISTORICAL FS'!I5,0) -> 0.21805386 | J10: =IFERROR('HISTORICAL FS'!J11/'HISTORICAL FS'!J5,0) -> 0.19807108 | ... L10: =IFERROR('HISTORICAL FS'!L11/'HISTORICAL FS'!L5,0) -> 0.23605715 | N10: =IFERROR(AVERAGE(C10:L10),0) -> 0.21800982 | O10: =IFERROR(MEDIAN(C10:L10),0) -> 0.21727688
B11: EBITDA Margin | C11: =IFERROR('HISTORICAL FS'!C18,0) -> 0.14910626 | D11: =IFERROR('HISTORICAL FS'!D18,0) -> 0.14061845 | E11: =IFERROR('HISTORICAL FS'!E18,0) -> 0.10971269 | F11: =IFERROR('HISTORICAL FS'!F18,0) -> 0.10789788 | G11: =IFERROR('HISTORICAL FS'!G18,0) -> 0.081686629 | H11: =IFERROR('HISTORICAL FS'!H18,0) -> 0.068898034 | I11: =IFERROR('HISTORICAL FS'!I18,0) -> 0.12925584 | J11: =IFERROR('HISTORICAL FS'!J18,0) -> 0.088776328 | ... L11: =IFERROR('HISTORICAL FS'!L18,0) -> 0.1359547 | N11: =IFERROR(AVERAGE(C11:L11),0) -> 0.11038688 | O11: =IFERROR(MEDIAN(C11:L11),0) -> 0.10880529
B12: EBIT Margin | C12: =IFERROR((('HISTORICAL FS'!C17-'HISTORICAL FS'!C23)/'HISTORICAL FS'!C5),0) -> 0.098229671 | D12: =IFERROR((('HISTORICAL FS'!D17-'HISTORICAL FS'!D23)/'HISTORICAL FS'!D5),0) -> 0.079417028 | E12: =IFERROR((('HISTORICAL FS'!E17-'HISTORICAL FS'!E23)/'HISTORICAL FS'!E5),0) -> 0.043322301 | F12: =IFERROR((('HISTORICAL FS'!F17-'HISTORICAL FS'!F23)/'HISTORICAL FS'!F5),0) -> 0.033970412 | G12: =IFERROR((('HISTORICAL FS'!G17-'HISTORICAL FS'!G23)/'HISTORICAL FS'!G5),0) -> 0.0035560233 | H12: =IFERROR((('HISTORICAL FS'!H17-'HISTORICAL FS'!H23)/'HISTORICAL FS'!H5),0) -> -0.013170363 | I12: =IFERROR((('HISTORICAL FS'!I17-'HISTORICAL FS'!I23)/'HISTORICAL FS'!I5),0) -> 0.034991608 | J12: =IFERROR((('HISTORICAL FS'!J17-'HISTORICAL FS'!J23)/'HISTORICAL FS'!J5),0) -> -0.00041514993 | ... L12: =IFERROR((('HISTORICAL FS'!L17-'HISTORICAL FS'!L23)/'HISTORICAL FS'!L5),0) -> 0.073683863 | N12: =IFERROR(AVERAGE(C12:L12),0) -> 0.037368974 | O12: =IFERROR(MEDIAN(C12:L12),0) -> 0.03448101
B13: EBT Margin | C13: =IFERROR('HISTORICAL FS'!C27,0) -> 0.082469388 | D13: =IFERROR('HISTORICAL FS'!D27,0) -> 0.051734106 | E13: =IFERROR('HISTORICAL FS'!E27,0) -> 0.034538557 | F13: =IFERROR('HISTORICAL FS'!F27,0) -> 0.038261059 | G13: =IFERROR('HISTORICAL FS'!G27,0) -> -0.10389917 | H13: =IFERROR('HISTORICAL FS'!H27,0) -> -0.040525768 | I13: =IFERROR('HISTORICAL FS'!I27,0) -> -0.041931546 | J13: =IFERROR('HISTORICAL FS'!J27,0) -> -0.025151083 | ... L13: =IFERROR('HISTORICAL FS'!L27,0) -> 0.063834979 | N13: =IFERROR(AVERAGE(C13:L13),0) -> 0.0069140501 | O13: =IFERROR(MEDIAN(C13:L13),0) -> 0.02217427
B14: Net Profit Margin | C14: =IFERROR('HISTORICAL FS'!C33,0) -> 0.05342645 | D14: =IFERROR('HISTORICAL FS'!D33,0) -> 0.040655187 | E14: =IFERROR('HISTORICAL FS'!E33,0) -> 0.022483235 | F14: =IFERROR('HISTORICAL FS'!F33,0) -> 0.023368509 | G14: =IFERROR('HISTORICAL FS'!G33,0) -> -0.0958265 | H14: =IFERROR('HISTORICAL FS'!H33,0) -> -0.042039742 | I14: =IFERROR('HISTORICAL FS'!I33,0) -> -0.05210734 | J14: =IFERROR('HISTORICAL FS'!J33,0) -> -0.040346755 | ... L14: =IFERROR('HISTORICAL FS'!L33,0) -> 0.072630128 | N14: =IFERROR(AVERAGE(C14:L14),0) -> -0.00099818949 | O14: =IFERROR(MEDIAN(C14:L14),0) -> 0.015129084
B16: Sales Expenses % Sales | C16: =IFERROR('HISTORICAL FS'!C15,0) -> 0.08004078 | D16: =IFERROR('HISTORICAL FS'!D15,0) -> 0.10672679 | E16: =IFERROR('HISTORICAL FS'!E15,0) -> 0.1284781 | F16: =IFERROR('HISTORICAL FS'!F15,0) -> 0.10860202 | G16: =IFERROR('HISTORICAL FS'!G15,0) -> 0.11402505 | H16: =IFERROR('HISTORICAL FS'!H15,0) -> 0.12527324 | I16: =IFERROR('HISTORICAL FS'!I15,0) -> 0.088798023 | J16: =IFERROR('HISTORICAL FS'!J15,0) -> 0.10929475 | ... L16: =IFERROR('HISTORICAL FS'!L15,0) -> 0.10010244 | N16: =IFERROR(AVERAGE(C16:L16),0) -> 0.10762294 | O16: =IFERROR(MEDIAN(C16:L16),0) -> 0.10894839
B17: Depriciation % Sales | C17: =IFERROR('HISTORICAL FS'!C24,0) -> 0.050876584 | D17: =IFERROR('HISTORICAL FS'!D24,0) -> 0.061201426 | E17: =IFERROR('HISTORICAL FS'!E24,0) -> 0.066390387 | F17: =IFERROR('HISTORICAL FS'!F24,0) -> 0.073927472 | G17: =IFERROR('HISTORICAL FS'!G24,0) -> 0.078130605 | H17: =IFERROR('HISTORICAL FS'!H24,0) -> 0.082068398 | I17: =IFERROR('HISTORICAL FS'!I24,0) -> 0.094264231 | J17: =IFERROR('HISTORICAL FS'!J24,0) -> 0.089191478 | ... L17: =IFERROR('HISTORICAL FS'!L24,0) -> 0.06227084 | N17: =IFERROR(AVERAGE(C17:L17),0) -> 0.073017903 | O17: =IFERROR(MEDIAN(C17:L17),0) -> 0.072892542
B18: Operating Income % Sales | C18: =IFERROR(C12,0) -> 0.098229671 | D18: =IFERROR(D12,0) -> 0.079417028 | E18: =IFERROR(E12,0) -> 0.043322301 | F18: =IFERROR(F12,0) -> 0.033970412 | G18: =IFERROR(G12,0) -> 0.0035560233 | H18: =IFERROR(H12,0) -> -0.013170363 | I18: =IFERROR(I12,0) -> 0.034991608 | J18: =IFERROR(J12,0) -> -0.00041514993 | ... L18: =IFERROR(L12,0) -> 0.073683863 | N18: =IFERROR(AVERAGE(C18:L18),0) -> 0.037368974 | O18: =IFERROR(MEDIAN(C18:L18),0) -> 0.03448101
B20: Return on Capital Employed | C20: =IFERROR(('HISTORICAL FS'!C17-'HISTORICAL FS'!C23)/('HISTORICAL FS'!C46+'HISTORICAL FS'!C47+'HISTORICAL FS'!C48),0) -> 0.19904181 | D20: =IFERROR(('HISTORICAL FS'!D17-'HISTORICAL FS'!D23)/('HISTORICAL FS'!D46+'HISTORICAL FS'!D47+'HISTORICAL FS'!D48),0) -> 0.1462081 | E20: =IFERROR(('HISTORICAL FS'!E17-'HISTORICAL FS'!E23)/('HISTORICAL FS'!E46+'HISTORICAL FS'!E47+'HISTORICAL FS'!E48),0) -> 0.085490986 | F20: =IFERROR(('HISTORICAL FS'!F17-'HISTORICAL FS'!F23)/('HISTORICAL FS'!F46+'HISTORICAL FS'!F47+'HISTORICAL FS'!F48),0) -> 0.053716114 | G20: =IFERROR(('HISTORICAL FS'!G17-'HISTORICAL FS'!G23)/('HISTORICAL FS'!G46+'HISTORICAL FS'!G47+'HISTORICAL FS'!G48),0) -> 0.0064542734 | H20: =IFERROR(('HISTORICAL FS'!H17-'HISTORICAL FS'!H23)/('HISTORICAL FS'!H46+'HISTORICAL FS'!H47+'HISTORICAL FS'!H48),0) -> -0.018302178 | I20: =IFERROR(('HISTORICAL FS'!I17-'HISTORICAL FS'!I23)/('HISTORICAL FS'!I46+'HISTORICAL FS'!I47+'HISTORICAL FS'!I48),0) -> 0.044284325 | J20: =IFERROR(('HISTORICAL FS'!J17-'HISTORICAL FS'!J23)/('HISTORICAL FS'!J46+'HISTORICAL FS'!J47+'HISTORICAL FS'!J48),0) -> -0.00060520306 | ... L20: =IFERROR(('HISTORICAL FS'!L17-'HISTORICAL FS'!L23)/('HISTORICAL FS'!L46+'HISTORICAL FS'!L47+'HISTORICAL FS'!L48),0) -> 0.16790573 | N20: =IFERROR(AVERAGE(C20:L20),0) -> 0.072295691 | O20: =IFERROR(MEDIAN(C20:L20),0) -> 0.049000219
B21: Retained Earning % | C21: =IFERROR('HISTORICAL FS'!C43,0) -> 1 | D21: =IFERROR('HISTORICAL FS'!D43,0) -> 0.99388148 | E21: =IFERROR('HISTORICAL FS'!E43,0) -> 1 | F21: =IFERROR('HISTORICAL FS'!F43,0) -> 1 | G21: =IFERROR('HISTORICAL FS'!G43,0) -> 0 | H21: =IFERROR('HISTORICAL FS'!H43,0) -> 0 | I21: =IFERROR('HISTORICAL FS'!I43,0) -> 0 | J21: =IFERROR('HISTORICAL FS'!J43,0) -> 0 | ... L21: =IFERROR('HISTORICAL FS'!L43,0) -> 0.92770403 | N21: =IFERROR(AVERAGE(C21:L21),0) -> 0.56368059 | O21: =IFERROR(MEDIAN(C21:L21),0) -> 0.82146223
B22: Return on Equity % | C22: =IFERROR('HISTORICAL FS'!C32/SUM('HISTORICAL FS'!C46:C47),0) -> 0.24989638 | D22: =IFERROR('HISTORICAL FS'!D32/SUM('HISTORICAL FS'!D46:D47),0) -> 0.14060014 | E22: =IFERROR('HISTORICAL FS'!E32/SUM('HISTORICAL FS'!E46:E47),0) -> 0.1044327 | F22: =IFERROR('HISTORICAL FS'!F32/SUM('HISTORICAL FS'!F46:F47),0) -> 0.071395255 | G22: =IFERROR('HISTORICAL FS'!G32/SUM('HISTORICAL FS'!G46:G47),0) -> -0.48078949 | H22: =IFERROR('HISTORICAL FS'!H32/SUM('HISTORICAL FS'!H46:H47),0) -> -0.17399312 | I22: =IFERROR('HISTORICAL FS'!I32/SUM('HISTORICAL FS'!I46:I47),0) -> -0.23560023 | J22: =IFERROR('HISTORICAL FS'!J32/SUM('HISTORICAL FS'!J46:J47),0) -> -0.25211821 | ... L22: =IFERROR('HISTORICAL FS'!L32/SUM('HISTORICAL FS'!L46:L47),0) -> 0.37455831 | N22: =IFERROR(AVERAGE(C22:L22),0) -> -0.014226778 | O22: =IFERROR(MEDIAN(C22:L22),0) -> 0.065372868
B23: Self Sustained Growth Rate | C23: =IFERROR(C21*C22,0) -> 0.24989638 | D23: =IFERROR(D21*D22,0) -> 0.13973988 | E23: =IFERROR(E21*E22,0) -> 0.1044327 | F23: =IFERROR(F21*F22,0) -> 0.071395255 | G23: =IFERROR(G21*G22,0) -> 0 | H23: =IFERROR(H21*H22,0) -> 0 | I23: =IFERROR(I21*I22,0) -> 0 | J23: =IFERROR(J21*J22,0) -> 0 | ... L23: =IFERROR(L21*L22,0) -> 0.34747925 | N23: =IFERROR(AVERAGE(C23:L23),0) -> 0.095539214 | O23: =IFERROR(MEDIAN(C23:L23),0) -> 0.056921966
B24: Interest Coverage Ratio | C24: =IFERROR(('HISTORICAL FS'!C17-'HISTORICAL FS'!C23)/'HISTORICAL FS'!C20,0) -> 5.317304 | D24: =IFERROR(('HISTORICAL FS'!D17-'HISTORICAL FS'!D23)/'HISTORICAL FS'!D20,0) -> 4.4352864 | E24: =IFERROR(('HISTORICAL FS'!E17-'HISTORICAL FS'!E23)/'HISTORICAL FS'!E20,0) -> 2.7568835 | F24: =IFERROR(('HISTORICAL FS'!F17-'HISTORICAL FS'!F23)/'HISTORICAL FS'!F20,0) -> 2.1154494 | G24: =IFERROR(('HISTORICAL FS'!G17-'HISTORICAL FS'!G23)/'HISTORICAL FS'!G20,0) -> 0.18645157 | H24: =IFERROR(('HISTORICAL FS'!H17-'HISTORICAL FS'!H23)/'HISTORICAL FS'!H20,0) -> -0.47469327 | I24: =IFERROR(('HISTORICAL FS'!I17-'HISTORICAL FS'!I23)/'HISTORICAL FS'!I20,0) -> 1.0794784 | J24: =IFERROR(('HISTORICAL FS'!J17-'HISTORICAL FS'!J23)/'HISTORICAL FS'!J20,0) -> -0.012414276 | ... L24: =IFERROR(('HISTORICAL FS'!L17-'HISTORICAL FS'!L23)/'HISTORICAL FS'!L20,0) -> 3.2314225 | N24: =IFERROR(AVERAGE(C24:L24),0) -> 1.9315375 | O24: =IFERROR(MEDIAN(C24:L24),0) -> 1.5974639
B26: Debtor Turnover Ratio | C26: =IFERROR('HISTORICAL FS'!C5/'HISTORICAL FS'!C58,0) -> 20.920168 | D26: =IFERROR('HISTORICAL FS'!D5/'HISTORICAL FS'!D58,0) -> 20.119918 | E26: =IFERROR('HISTORICAL FS'!E5/'HISTORICAL FS'!E58,0) -> 19.160353 | F26: =IFERROR('HISTORICAL FS'!F5/'HISTORICAL FS'!F58,0) -> 14.655712 | G26: =IFERROR('HISTORICAL FS'!G5/'HISTORICAL FS'!G58,0) -> 15.894699 | H26: =IFERROR('HISTORICAL FS'!H5/'HISTORICAL FS'!H58,0) -> 23.366617 | I26: =IFERROR('HISTORICAL FS'!I5/'HISTORICAL FS'!I58,0) -> 19.701331 | J26: =IFERROR('HISTORICAL FS'!J5/'HISTORICAL FS'!J58,0) -> 22.379918 | ... L26: =IFERROR('HISTORICAL FS'!L5/'HISTORICAL FS'!L58,0) -> 25.833688 | N26: =IFERROR(AVERAGE(C26:L26),0) -> 20.401535 | O26: =IFERROR(MEDIAN(C26:L26),0) -> 20.520043
B27: Creditor Turnover Ratio | C27: =IFERROR('HISTORICAL FS'!C5/'HISTORICAL FS'!C49,0) -> 2.4493011 | D27: =IFERROR('HISTORICAL FS'!D5/'HISTORICAL FS'!D49,0) -> 2.3769604 | E27: =IFERROR('HISTORICAL FS'!E5/'HISTORICAL FS'!E49,0) -> 1.9842808 | F27: =IFERROR('HISTORICAL FS'!F5/'HISTORICAL FS'!F49,0) -> 2.041478 | G27: =IFERROR('HISTORICAL FS'!G5/'HISTORICAL FS'!G49,0) -> 2.1667848 | H27: =IFERROR('HISTORICAL FS'!H5/'HISTORICAL FS'!H49,0) -> 1.9731057 | I27: =IFERROR('HISTORICAL FS'!I5/'HISTORICAL FS'!I49,0) -> 1.7323685 | J27: =IFERROR('HISTORICAL FS'!J5/'HISTORICAL FS'!J49,0) -> 2.0170312 | ... L27: =IFERROR('HISTORICAL FS'!L5/'HISTORICAL FS'!L49,0) -> 2.4694234 | N27: =IFERROR(AVERAGE(C27:L27),0) -> 2.143934 | O27: =IFERROR(MEDIAN(C27:L27),0) -> 2.1041314
B28: Inventory Turnover Ratio | C28: =IFERROR('HISTORICAL FS'!C5/'HISTORICAL FS'!C59,0) -> 8.990022 | D28: =IFERROR('HISTORICAL FS'!D5/'HISTORICAL FS'!D59,0) -> 8.3613381 | E28: =IFERROR('HISTORICAL FS'!E5/'HISTORICAL FS'!E59,0) -> 7.6867643 | F28: =IFERROR('HISTORICAL FS'!F5/'HISTORICAL FS'!F59,0) -> 6.9190052 | G28: =IFERROR('HISTORICAL FS'!G5/'HISTORICAL FS'!G59,0) -> 7.7392856 | H28: =IFERROR('HISTORICAL FS'!H5/'HISTORICAL FS'!H59,0) -> 6.9698269 | I28: =IFERROR('HISTORICAL FS'!I5/'HISTORICAL FS'!I59,0) -> 6.9217099 | J28: =IFERROR('HISTORICAL FS'!J5/'HISTORICAL FS'!J59,0) -> 7.9015588 | ... L28: =IFERROR('HISTORICAL FS'!L5/'HISTORICAL FS'!L59,0) -> 9.1639138 | N28: =IFERROR(AVERAGE(C28:L28),0) -> 7.9142289 | O28: =IFERROR(MEDIAN(C28:L28),0) -> 7.8204222
B29: Fixed Asset Turnover | C29: =IFERROR('HISTORICAL FS'!C5/'HISTORICAL FS'!C52,0) -> 2.9742371 | D29: =IFERROR('HISTORICAL FS'!D5/'HISTORICAL FS'!D52,0) -> 2.5463128 | E29: =IFERROR('HISTORICAL FS'!E5/'HISTORICAL FS'!E52,0) -> 2.8109343 | F29: =IFERROR('HISTORICAL FS'!F5/'HISTORICAL FS'!F52,0) -> 2.4012949 | G29: =IFERROR('HISTORICAL FS'!G5/'HISTORICAL FS'!G52,0) -> 2.714432 | H29: =IFERROR('HISTORICAL FS'!H5/'HISTORICAL FS'!H52,0) -> 2.0539206 | I29: =IFERROR('HISTORICAL FS'!I5/'HISTORICAL FS'!I52,0) -> 1.8008727 | J29: =IFERROR('HISTORICAL FS'!J5/'HISTORICAL FS'!J52,0) -> 2.0053489 | ... L29: =IFERROR('HISTORICAL FS'!L5/'HISTORICAL FS'!L52,0) -> 3.6107195 | N29: =IFERROR(AVERAGE(C29:L29),0) -> 2.5537452 | O29: =IFERROR(MEDIAN(C29:L29),0) -> 2.582846
B30: Capital Turnover | C30: =IFERROR('HISTORICAL FS'!C5/SUM('HISTORICAL FS'!C46:C47),0) -> 4.6773907 | D30: =IFERROR('HISTORICAL FS'!D5/SUM('HISTORICAL FS'!D46:D47),0) -> 3.4583567 | E30: =IFERROR('HISTORICAL FS'!E5/SUM('HISTORICAL FS'!E46:E47),0) -> 4.6449144 | F30: =IFERROR('HISTORICAL FS'!F5/SUM('HISTORICAL FS'!F46:F47),0) -> 3.0551909 | G30: =IFERROR('HISTORICAL FS'!G5/SUM('HISTORICAL FS'!G46:G47),0) -> 5.0172916 | H30: =IFERROR('HISTORICAL FS'!H5/SUM('HISTORICAL FS'!H46:H47),0) -> 4.138777 | I30: =IFERROR('HISTORICAL FS'!I5/SUM('HISTORICAL FS'!I46:I47),0) -> 4.5214404 | J30: =IFERROR('HISTORICAL FS'!J5/SUM('HISTORICAL FS'!J46:J47),0) -> 6.2487853 | ... L30: =IFERROR('HISTORICAL FS'!L5/SUM('HISTORICAL FS'!L46:L47),0) -> 5.1570652 | N30: =IFERROR(AVERAGE(C30:L30),0) -> 4.855278 | O30: =IFERROR(MEDIAN(C30:L30),0) -> 4.6611525
B32: Debtor Days | C32: =IFERROR(365/C26,0) -> 17.447278 | D32: =IFERROR(365/D26,0) -> 18.141227 | E32: =IFERROR(365/E26,0) -> 19.049753 | F32: =IFERROR(365/F26,0) -> 24.904965 | G32: =IFERROR(365/G26,0) -> 22.963631 | H32: =IFERROR(365/H26,0) -> 15.620575 | I32: =IFERROR(365/I26,0) -> 18.526667 | J32: =IFERROR(365/J26,0) -> 16.309265 | ... L32: =IFERROR(365/L26,0) -> 14.128838 | N32: =IFERROR(AVERAGE(C32:L32),0) -> 18.369598 | O32: =IFERROR(MEDIAN(C32:L32),0) -> 17.794253
B33: Payable Days | C33: =IFERROR(365/C27,0) -> 149.02211 | D33: =IFERROR(365/D27,0) -> 153.55746 | E33: =IFERROR(365/E27,0) -> 183.94574 | F33: =IFERROR(365/F27,0) -> 178.79203 | G33: =IFERROR(365/G27,0) -> 168.45236 | H33: =IFERROR(365/H27,0) -> 184.98755 | I33: =IFERROR(365/I27,0) -> 210.69421 | J33: =IFERROR(365/J27,0) -> 180.95902 | ... L33: =IFERROR(365/L27,0) -> 147.80778 | N33: =IFERROR(AVERAGE(C33:L33),0) -> 172.19978 | O33: =IFERROR(MEDIAN(C33:L33),0) -> 173.62219
B34: Inventory Days | C34: =IFERROR(365/C28,0) -> 40.600568 | D34: =IFERROR(365/D28,0) -> 43.6533 | E34: =IFERROR(365/E28,0) -> 47.484219 | F34: =IFERROR(365/F28,0) -> 52.753249 | G34: =IFERROR(365/G28,0) -> 47.161976 | H34: =IFERROR(365/H28,0) -> 52.368589 | I34: =IFERROR(365/I28,0) -> 52.732635 | J34: =IFERROR(365/J28,0) -> 46.193417 | ... L34: =IFERROR(365/L28,0) -> 39.830143 | N34: =IFERROR(AVERAGE(C34:L34),0) -> 46.57756 | O34: =IFERROR(MEDIAN(C34:L34),0) -> 46.677696
B35: Cash Conversion Cycle | C35: =SUM(C32,C34)-C33 -> -90.974259 | D35: =SUM(D32,D34)-D33 -> -91.762933 | E35: =SUM(E32,E34)-E33 -> -117.41177 | F35: =SUM(F32,F34)-F33 -> -101.13382 | G35: =SUM(G32,G34)-G33 -> -98.326751 | H35: =SUM(H32,H34)-H33 -> -116.99839 | I35: =SUM(I32,I34)-I33 -> -139.4349 | J35: =SUM(J32,J34)-J33 -> -118.45634 | ... L35: =SUM(L32,L34)-L33 -> -93.848801 | N35: =IFERROR(AVERAGE(C35:L35),0) -> -107.25262 | O35: =IFERROR(MEDIAN(C35:L35),0) -> -102.65603
B37: CFO/SALES | C37: =IFERROR('HISTORICAL FS'!C78/'HISTORICAL FS'!C5,0) -> 0.13502104 | D37: =IFERROR('HISTORICAL FS'!D78/'HISTORICAL FS'!D5,0) -> 0.13880099 | E37: =IFERROR('HISTORICAL FS'!E78/'HISTORICAL FS'!E5,0) -> 0.11197938 | F37: =IFERROR('HISTORICAL FS'!F78/'HISTORICAL FS'!F5,0) -> 0.081828025 | G37: =IFERROR('HISTORICAL FS'!G78/'HISTORICAL FS'!G5,0) -> 0.062569054 | H37: =IFERROR('HISTORICAL FS'!H78/'HISTORICAL FS'!H5,0) -> 0.10201558 | I37: =IFERROR('HISTORICAL FS'!I78/'HISTORICAL FS'!I5,0) -> 0.11609531 | J37: =IFERROR('HISTORICAL FS'!J78/'HISTORICAL FS'!J5,0) -> 0.051290409 | ... L37: =IFERROR('HISTORICAL FS'!L78/'HISTORICAL FS'!L5,0) -> 0.15508494 | N37: =IFERROR(AVERAGE(C37:L37),0) -> 0.1056972 | O37: =IFERROR(MEDIAN(C37:L37),0) -> 0.1071333
B38: CFO/TOTAL ASSETS | C38: =IFERROR('HISTORICAL FS'!C78/'HISTORICAL FS'!C63,0) -> 0.14972518 | D38: =IFERROR('HISTORICAL FS'!D78/'HISTORICAL FS'!D63,0) -> 0.14400185 | E38: =IFERROR('HISTORICAL FS'!E78/'HISTORICAL FS'!E63,0) -> 0.11079302 | F38: =IFERROR('HISTORICAL FS'!F78/'HISTORICAL FS'!F63,0) -> 0.072914417 | G38: =IFERROR('HISTORICAL FS'!G78/'HISTORICAL FS'!G63,0) -> 0.061798444 | H38: =IFERROR('HISTORICAL FS'!H78/'HISTORICAL FS'!H63,0) -> 0.083181494 | I38: =IFERROR('HISTORICAL FS'!I78/'HISTORICAL FS'!I63,0) -> 0.084902092 | J38: =IFERROR('HISTORICAL FS'!J78/'HISTORICAL FS'!J63,0) -> 0.043402222 | ... L38: =IFERROR('HISTORICAL FS'!L78/'HISTORICAL FS'!L63,0) -> 0.18379489 | N38: =IFERROR(AVERAGE(C38:L38),0) -> 0.10402522 | O38: =IFERROR(MEDIAN(C38:L38),0) -> 0.095320338
B39: CFO/TOTAL DEBT | C39: =IFERROR('HISTORICAL FS'!C78/'HISTORICAL FS'!C48,0) -> 0.4827036 | D39: =IFERROR('HISTORICAL FS'!D78/'HISTORICAL FS'!D48,0) -> 0.54641035 | E39: =IFERROR('HISTORICAL FS'!E78/'HISTORICAL FS'!E48,0) -> 0.38420446 | F39: =IFERROR('HISTORICAL FS'!F78/'HISTORICAL FS'!F48,0) -> 0.26820544 | G39: =IFERROR('HISTORICAL FS'!G78/'HISTORICAL FS'!G48,0) -> 0.17793209 | H39: =IFERROR('HISTORICAL FS'!H78/'HISTORICAL FS'!H48,0) -> 0.21342659 | I39: =IFERROR('HISTORICAL FS'!I78/'HISTORICAL FS'!I48,0) -> 0.20403774 | J39: =IFERROR('HISTORICAL FS'!J78/'HISTORICAL FS'!J48,0) -> 0.097521984 | ... L39: =IFERROR('HISTORICAL FS'!L78/'HISTORICAL FS'!L48,0) -> 0.63317562 | N39: =IFERROR(AVERAGE(C39:L39),0) -> 0.3271484 | O39: =IFERROR(MEDIAN(C39:L39),0) -> 0.26603581

Sheet STATEMENTS
D3: 2020 | E3: 2021 | F3: 2022 | G3: 2023 | H3: 2024 | I3: 2025 | J3: 2026
B4: TATA STEELS
B5: INR(CRORES) | D5: 2020 | E5: 2021 | F5: 2022 | G5: 2023 | H5: 2024 | I5: 2025 | J5: 2026
B7: ="Income Statement"&"-" & B4 -> Income Statement-TATA STEELS
B8: Revenue | D8: 20000 | E8: 22500 | F8: =E8*(1+F23) -> 24750 | G8: =F8*(1+G23) -> 27225 | H8: =G8*(1+H23) -> 31308.75 | I8: =H8*(1+I23) -> 36005.063 | J8: =I8*(1+J23) -> 41405.822
B9: COGS | D9: 8000 | E9: 9000 | F9: =F8*F24 -> 9900 | G9: =G8*G24 -> 10890 | H9: =H8*H24 -> 12523.5 | I9: =I8*I24 -> 14402.025 | J9: =J8*J24 -> 16562.329
B10: Gross Profit | D10: =D8-D9 -> 12000 | E10: 13500 | F10: =F8-F9 -> 14850 | G10: =G8-G9 -> 16335 | H10: =H8-H9 -> 18785.25 | I10: =I8-I9 -> 21603.038 | J10: =J8-J9 -> 24843.493
B11: Selling and G. Expenses | D11: 2000 | E11: 2250 | F11: =F25 -> 2500 | G11: =F11 -> 2500 | H11: =G11 -> 2500 | I11: =H11 -> 2500 | J11: =I11 -> 2500
B12: EBITDA | D12: =D10-D11 -> 10000 | E12: 11250 | F12: =F10-F11 -> 12350 | G12: =G10-G11 -> 13835 | H12: =H10-H11 -> 16285.25 | I12: =I10-I11 -> 19103.038 | J12: =J10-J11 -> 22343.493
B13: Depriciation | D13: 800 | E13: 900 | F13: =F8*F26 -> 1237.5 | G13: =G8*G26 -> 1361.25 | H13: =H8*H26 -> 1565.4375 | I13: =I8*I26 -> 1800.2531 | J13: =J8*J26 -> 2070.2911
B14: Interest | D14: 200 | E14: 225 | F14: =F27 -> 250 | G14: =F14 -> 250 | H14: =G14 -> 250 | I14: =H14 -> 250 | J14: =I14 -> 250
B15: EBT | D15: =D12-SUM(D13:D14) -> 9000 | E15: 10125 | F15: =F12-SUM(F13:F14) -> 10862.5 | G15: =G12-SUM(G13:G14) -> 12223.75 | H15: =H12-SUM(H13:H14) -> 14469.813 | I15: =I12-SUM(I13:I14) -> 17052.784 | J15: =J12-SUM(J13:J14) -> 20023.202
B16: Taxes | D16: 2700 | E16: 3038 | F16: =F15*F28 -> 3258.75 | G16: =G15*G28 -> 3667.125 | H16: =H15*H28 -> 4340.9438 | I16: =I15*I28 -> 5115.8353 | J16: =J15*J28 -> 6006.9606
B17: Net Income | D17: =D15-D16 -> 6300 | E17: 7088 | F17: =F15-F16 -> 7603.75 | G17: =G15-G16 -> 8556.625 | H17: =H15-H16 -> 10128.869 | I17: =I15-I16 -> 11936.949 | J17: =J15-J16 -> 14016.241
B22: ="Assumption Drivers"&"-"&B4 -> Assumption Drivers-TATA STEELS
B23: Revenue Growth | D23: NA | E23: =E8/D8-1 -> 0.125 | F23: 0.1 | G23: =F23 -> 0.1 | H23: 0.15 | I23: =H23 -> 0.15 | J23: =I23 -> 0.15
B24: COGS % of R | D24: =D9/D8 -> 0.4 | E24: =E9/E8 -> 0.4 | F24: 0.4 | G24: =F24 -> 0.4 | H24: =G24 -> 0.4 | I24: =H24 -> 0.4 | J24: =I24 -> 0.4
B25: S & G Expenses | D25: 2000 | E25: 2250 | F25: 2500 | G25: =F25 -> 2500 | H25: =G25 -> 2500 | I25: =H25 -> 2500 | J25: =I25 -> 2500
B26: Depriciation % Sales | D26: =D13/D8 -> 0.04 | E26: =E13/E8 -> 0.04 | F26: 0.05 | G26: =F26 -> 0.05 | H26: =G26 -> 0.05 | I26: =H26 -> 0.05 | J26: =I26 -> 0.05
B27: Interest | D27: 200 | E27: 225 | F27: 250 | G27: 250 | H27: 250 | I27: 250 | J27: 250
B28: Taxes | D28: 0.3 | E28: 0.3 | F28: 0.3 | G28: =F28 -> 0.3 | H28: =G28 -> 0.3 | I28: =H28 -> 0.3 | J28: =I28 -> 0.3
B33: ="Common Size Statement"&"-"&B4 -> Common Size Statement-TATA STEELS
B34: Revenue | D34: 1 | E34: =E8/E$9 -> 2.5 | F34: =F8/F$9 -> 2.5 | G34: =G8/G$9 -> 2.5 | H34: =H8/H$9 -> 2.5 | I34: =I8/I$9 -> 2.5 | J34: =J8/J$9 -> 2.5
B35: COGS | D35: 0.4 | E35: =E9/E$9 -> 1 | F35: =F9/F$9 -> 1 | G35: =G9/G$9 -> 1 | H35: =H9/H$9 -> 1 | I35: =I9/I$9 -> 1 | J35: =J9/J$9 -> 1
B36: Gross Profit | D36: =D10/D$9 -> 1.5 | E36: =E10/E$9 -> 1.5 | F36: =F10/F$9 -> 1.5 | G36: =G10/G$9 -> 1.5 | H36: =H10/H$9 -> 1.5 | I36: =I10/I$9 -> 1.5 | J36: =J10/J$9 -> 1.5
B37: Selling and G. Expenses | D37: =D11/D$9 -> 0.25 | E37: =E11/E$9 -> 0.25 | F37: =F11/F$9 -> 0.25252525 | G37: =G11/G$9 -> 0.22956841 | H37: =H11/H$9 -> 0.19962471 | I37: =I11/I$9 -> 0.1735867 | J37: =J11/J$9 -> 0.15094496
B38: EBITDA | D38: =D12/D$9 -> 1.25 | E38: =E12/E$9 -> 1.25 | F38: =F12/F$9 -> 1.2474747 | G38: =G12/G$9 -> 1.2704316 | H38: =H12/H$9 -> 1.3003753 | I38: =I12/I$9 -> 1.3264133 | J38: =J12/J$9 -> 1.349055
B39: Depriciation | D39: =D13/D$9 -> 0.1 | E39: =E13/E$9 -> 0.1 | F39: =F13/F$9 -> 0.125 | G39: =G13/G$9 -> 0.125 | H39: =H13/H$9 -> 0.125 | I39: =I13/I$9 -> 0.125 | J39: =J13/J$9 -> 0.125
B40: Interest | D40: =D14/D$9 -> 0.025 | E40: =E14/E$9 -> 0.025 | F40: =F14/F$9 -> 0.025252525 | G40: =G14/G$9 -> 0.022956841 | H40: =H14/H$9 -> 0.019962471 | I40: =I14/I$9 -> 0.01735867 | J40: =J14/J$9 -> 0.015094496
B41: EBT | D41: =D15/D$9 -> 1.125 | E41: =E15/E$9 -> 1.125 | F41: =F15/F$9 -> 1.0972222 | G41: =G15/G$9 -> 1.1224747 | H41: =H15/H$9 -> 1.1554128 | I41: =I15/I$9 -> 1.1840546 | J41: =J15/J$9 -> 1.2089605
B42: Taxes | D42: =D16/D$9 -> 0.3375 | E42: =E16/E$9 -> 0.33755556 | F42: =F16/F$9 -> 0.32916667 | G42: =G16/G$9 -> 0.33674242 | H42: =H16/H$9 -> 0.34662385 | I42: =I16/I$9 -> 0.35521639 | J42: =J16/J$9 -> 0.36268816
B43: Net Income | D43: =D17/D$9 -> 0.7875 | E43: =E17/E$9 -> 0.78755556 | F43: =F17/F$9 -> 0.76805556 | G43: =G17/G$9 -> 0.78573232 | H43: =H17/H$9 -> 0.80878898 | I43: =I17/I$9 -> 0.82883824 | J43: =J17/J$9 -> 0.84627238
B46: ="Change Analysis Statement"&"-"&B4 -> Change Analysis Statement-TATA STEELS
C47: 0.1
B48: Revenue | D48: =D8*(1+$C$48) -> 20000 | E48: =E8*(1+$C$48) -> 22500 | F48: =F8*(1+$C$48) -> 24750 | G48: =G8*(1+$C$48) -> 27225 | H48: =H8*(1+$C$48) -> 31308.75 | I48: =I8*(1+$C$48) -> 36005.063 | J48: =J8*(1+$C$48) -> 41405.822
B49: COGS | D49: =D9*(1+$C$48) -> 8000 | E49: =E9*(1+$C$48) -> 9000 | F49: =F9*(1+$C$48) -> 9900 | G49: =G9*(1+$C$48) -> 10890 | H49: =H9*(1+$C$48) -> 12523.5 | I49: =I9*(1+$C$48) -> 14402.025 | J49: =J9*(1+$C$48) -> 16562.329
B50: Gross Profit | D50: =D10*(1+$C$48) -> 12000 | E50: =E10*(1+$C$48) -> 13500 | F50: =F10*(1+$C$48) -> 14850 | G50: =G10*(1+$C$48) -> 16335 | H50: =H10*(1+$C$48) -> 18785.25 | I50: =I10*(1+$C$48) -> 21603.038 | J50: =J10*(1+$C$48) -> 24843.493
B51: Selling Expenses | D51: =D11*(1+$C$48) -> 2000 | E51: =E11*(1+$C$48) -> 2250 | F51: =F11*(1+$C$48) -> 2500 | G51: =G11*(1+$C$48) -> 2500 | H51: =H11*(1+$C$48) -> 2500 | I51: =I11*(1+$C$48) -> 2500 | J51: =J11*(1+$C$48) -> 2500
B52: EBITDA | D52: =D12*(1+$C$48) -> 10000 | E52: =E12*(1+$C$48) -> 11250 | F52: =F12*(1+$C$48) -> 12350 | G52: =G12*(1+$C$48) -> 13835 | H52: =H12*(1+$C$48) -> 16285.25 | I52: =I12*(1+$C$48) -> 19103.038 | J52: =J12*(1+$C$48) -> 22343.493
B53: Depriciation | D53: =D13*(1+$C$48) -> 800 | E53: =E13*(1+$C$48) -> 900 | F53: =F13*(1+$C$48) -> 1237.5 | G53: =G13*(1+$C$48) -> 1361.25 | H53: =H13*(1+$C$48) -> 1565.4375 | I53: =I13*(1+$C$48) -> 1800.2531 | J53: =J13*(1+$C$48) -> 2070.2911
B54: Interest | D54: =D14*(1+$C$48) -> 200 | E54: =E14*(1+$C$48) -> 225 | F54: =F14*(1+$C$48) -> 250 | G54: =G14*(1+$C$48) -> 250 | H54: =H14*(1+$C$48) -> 250 | I54: =I14*(1+$C$48) -> 250 | J54: =J14*(1+$C$48) -> 250
B55: EBT | D55: =D15*(1+$C$48) -> 9000 | E55: =E15*(1+$C$48) -> 10125 | F55: =F15*(1+$C$48) -> 10862.5 | G55: =G15*(1+$C$48) -> 12223.75 | H55: =H15*(1+$C$48) -> 14469.813 | I55: =I15*(1+$C$48) -> 17052.784 | J55: =J15*(1+$C$48) -> 20023.202
B56: Taxes | D56: =D16*(1+$C$48) -> 2700 | E56: =E16*(1+$C$48) -> 3038 | F56: =F16*(1+$C$48) -> 3258.75 | G56: =G16*(1+$C$48) -> 3667.125 | H56: =H16*(1+$C$48) -> 4340.9438 | I56: =I16*(1+$C$48) -> 5115.8353 | J56: =J16*(1+$C$48) -> 6006.9606
B57: Net Income | D57: =D17*(1+$C$48) -> 6300 | E57: =E17*(1+$C$48) -> 7088 | F57: =F17*(1+$C$48) -> 7603.75 | G57: =G17*(1+$C$48) -> 8556.625 | H57: =H17*(1+$C$48) -> 10128.869 | I57: =I17*(1+$C$48) -> 11936.949 | J57: =J17*(1+$C$48) -> 14016.241
B59: Time Periods | C59: 44788 | D59: 0 | E59: 1 | F59: 2 | G59: 3 | H59: 4 | I59: 5 | J59: 6
B60: Monthly Data | D60: =EOMONTH($C$60,D59) -> 31 | E60: =EOMONTH($C$60,E59) -> 59 | F60: =EOMONTH($C$60,F59) -> 91 | G60: =EOMONTH($C$60,G59) -> 121 | H60: =EOMONTH($C$60,H59) -> 152 | I60: =EOMONTH($C$60,I59) -> 182 | J60: =EOMONTH($C$60,J59) -> 213
B61: Annual Data | D61: =DATE(YEAR($C$60)+D59,12,31) -> 366 | E61: =DATE(YEAR($C$60)+E59,12,31) -> 731 | F61: =DATE(YEAR($C$60)+F59,12,31) -> 1096 | G61: =DATE(YEAR($C$60)+G59,12,31) -> 1461 | H61: =DATE(YEAR($C$60)+H59,12,31) -> 1827 | I61: =DATE(YEAR($C$60)+I59,12,31) -> 2192 | J61: =DATE(YEAR($C$60)+J59,12,31) -> 2557
B63: Monthly Period | D63: =YEARFRAC($C$60,D60) -> 0.086111111 | E63: =YEARFRAC($C$60,E60) -> 0.16111111 | F63: =YEARFRAC($C$60,F60) -> 0.25277778 | G63: =YEARFRAC($C$60,G60) -> 0.33333333 | H63: =YEARFRAC($C$60,H60) -> 0.41944444 | I63: =YEARFRAC($C$60,I60) -> 0.5 | J63: =YEARFRAC($C$60,J60) -> 0.58611111
B64: Annual Period | D64: =YEARFRAC($C$60,D61) -> 1.0027778 | E64: =YEARFRAC($C$60,E61) -> 2.0027778 | F64: =YEARFRAC($C$60,F61) -> 3.0027778 | G64: =YEARFRAC($C$60,G61) -> 4.0027778 | H64: =YEARFRAC($C$60,H61) -> 5.0027778 | I64: =YEARFRAC($C$60,I61) -> 6.0027778 | J64: =YEARFRAC($C$60,J61) -> 7.0027778
B65: STUB YEAR OR FULL YEAR | D65: =IF(D64<1,"STUB","FULL YEAR") -> FULL YEAR | E65: =IF(E64<1,"STUB","FULL YEAR") -> FULL YEAR | F65: =IF(F64<1,"STUB","FULL YEAR") -> FULL YEAR | G65: =IF(G64<1,"STUB","FULL YEAR") -> FULL YEAR | H65: =IF(H64<1,"STUB","FULL YEAR") -> FULL YEAR | I65: =IF(I64<1,"STUB","FULL YEAR") -> FULL YEAR | J65: =IF(J64<1,"STUB","FULL YEAR") -> FULL YEAR
B67: COSTING ANALYSIS
B69: COGS | C69: 0.1 | D69: 8000 | E69: 9000 | F69: 9900 | G69: 10890 | H69: 12523.5 | I69: 14402.025 | J69: 16562.329
B70: Selling Expenses | C70: 0.2 | D70: 2000 | E70: 2250 | F70: 2500 | G70: 2500 | H70: 2500 | I70: 2500 | J70: 2500
B71: Depriciation | C71: 0.2 | D71: 800 | E71: 900 | F71: 1237.5 | G71: 1361.25 | H71: 1565.4375 | I71: 1800.2531 | J71: 2070.2911
B72: Interest | C72: 0.3 | D72: 200 | E72: 225 | F72: 250 | G72: 250 | H72: 250 | I72: 250 | J72: 250
B73: Taxes | C73: 0.2 | D73: 2700 | E73: 3038 | F73: 3258.75 | G73: 3667.125 | H73: 4340.9438 | I73: 5115.8353 | J73: 6006.9606
B74: Total | D74: =SUM(D69:D73) -> 13700 | E74: =SUM(E69:E73) -> 15413 | F74: =SUM(F69:F73) -> 17146.25 | G74: =SUM(G69:G73) -> 18668.375 | H74: =SUM(H69:H73) -> 21179.881 | I74: =SUM(I69:I73) -> 24068.113 | J74: =SUM(J69:J73) -> 27389.58
B77: AVERAGE | D77: =AVERAGE(D69:D73) -> 2740 | E77: =AVERAGE(E69:E73) -> 3082.6 | F77: =AVERAGE(F69:F73) -> 3429.25 | G77: =AVERAGE(G69:G73) -> 3733.675 | H77: =AVERAGE(H69:H73) -> 4235.9763 | I77: =AVERAGE(I69:I73) -> 4813.6227 | J77: =AVERAGE(J69:J73) -> 5477.9161
B78: WEIGHTED AVERAGE | D78: =SUMPRODUCT($C$70:$C$74,D69:D73) -> 2280 | E78: =SUMPRODUCT($C$70:$C$74,E69:E73) -> 2565 | F78: =SUMPRODUCT($C$70:$C$74,F69:F73) -> 2901.25 | G78: =SUMPRODUCT($C$70:$C$74,G69:G73) -> 3136.375 | H78: =SUMPRODUCT($C$70:$C$74,H69:H73) -> 3524.3313 | I78: =SUMPRODUCT($C$70:$C$74,I69:I73) -> 3970.4809 | J78: =SUMPRODUCT($C$70:$C$74,J69:J73) -> 4483.5531
B80: MEDIAN | D80: 2000 | E80: 2250 | F80: 2500 | G80: 2500 | H80: 2500 | I80: 2500 | J80: 2500
B81: MIN | D81: =MIN(D69:D73) -> 200 | E81: =MIN(E69:E73) -> 225 | F81: =MIN(F69:F73) -> 250 | G81: =MIN(G69:G73) -> 250 | H81: =MIN(H69:H73) -> 250 | I81: =MIN(I69:I73) -> 250 | J81: =MIN(J69:J73) -> 250
B82: MAX | D82: =MAX(D69:D73) -> 8000 | E82: =MAX(E69:E73) -> 9000 | F82: =MAX(F69:F73) -> 9900 | G82: =MAX(G69:G73) -> 10890 | H82: =MAX(H69:H73) -> 12523.5 | I82: =MAX(I69:I73) -> 14402.025 | J82: =MAX(J69:J73) -> 16562.329
B83: SMALL | C83: 2 | D83: =SMALL(D69:D73,$C$84) -> 2000 | E83: =SMALL(E69:E73,$C$84) -> 2250 | F83: =SMALL(F69:F73,$C$84) -> 2500 | G83: =SMALL(G69:G73,$C$84) -> 2500 | H83: =SMALL(H69:H73,$C$84) -> 2500 | I83: =SMALL(I69:I73,$C$84) -> 2500 | J83: =SMALL(J69:J73,$C$84) -> 2500
B84: LARGE | C84: 3 | D84: 2000 | E84: 2250 | F84: 2500 | G84: 2500 | H84: 2500 | I84: 2500 | J84: 2500
B87: TOTAL EXPENSES
B88: if<17500 | C88: 17500 | D88: =IF(D74<$C$89,D74,0) -> 13700 | E88: =IF(E74<$C$89,E74,0) -> 15413 | F88: =IF(F74<$C$89,F74,0) -> 17146.25 | G88: =IF(G74<$C$89,G74,0) -> 0 | H88: =IF(H74<$C$89,H74,0) -> 0 | I88: =IF(I74<$C$89,I74,0) -> 0 | J88: =IF(J74<$C$89,J74,0) -> 0
B89: if>=17500 | C89: 17500

Sheet RAW DATA
A1: INCOME STATEMENT | C1: 2020 | D1: 2021 | F1: 2022 | G1: 2023 | H1: 2024
A2: Revenue | C2: 20000 | D2: 22500
A3: COGS | C3: 8000 | D3: 9000
A4: Gross Profit | C4: =(C2-C3) -> 12000 | D4: 13500
A5: Selling and General Expenses | C5: 2000 | D5: 2250
A6: EBITDA | C6: 10000 | D6: 11250
A7: Depriciation | C7: 800 | D7: 900
A8: Interest | C8: 200 | D8: 225
A9: EBT | C9: 9000 | D9: 10125
A10: Taxes | C10: 2700 | D10: 3038
A11: Net Income | C11: 6300 | D11: 7088

Sheet PEER COMPARISON
B2: Peer Comp
H4: Debt/ | I4: Debt/ | J4: Levered | K4: Unlevered
E5: Total Debt | F5: Total Equity | G5: Tax Rate 1 | H5: Equity | I5: Capital | J5: Beta 2 | K5: Beta 3
B6: Avenue Super. | D6: India | E6: =[1]Sheet1!P2 -> 712.91 | F6: =[1]Sheet1!N2 -> 281370.49 | G6: 0.3 | H6: =E6/F6 -> 0.0025337056 | I6: =E6/SUM(E6:F6) -> 0.0025273022 | J6: =[2]Sheet1!$P$7 -> 1.0622811 | K6: =J6/(1+(1-G6)*H6) -> 1.0604004
B7: Trent | D7: India | E7: =[1]Sheet1!P3 -> 1842.2 | F7: =[1]Sheet1!N3 -> 185816.8 | G7: 0.3 | H7: =E7/F7 -> 0.0099140659 | I7: =E7/SUM(E7:F7) -> 0.0098167421 | J7: 1.11 | K7: =J7/(1+(1-G7)*H7) -> 1.1023499
B8: Aditya Bir. Fas. | D8: India | E8: =[1]Sheet1!P4 -> 9999.18 | F8: =[1]Sheet1!N4 -> 33165.94 | G8: 0.3 | H8: =E8/F8 -> 0.30148942 | I8: =E8/SUM(E8:F8) -> 0.23164954 | J8: 1.43 | K8: =J8/(1+(1-G8)*H8) -> 1.1808007
B9: Brainbees Solut. | D9: India | E9: =[1]Sheet1!P5 -> 1573.61 | F9: =[1]Sheet1!N5 -> 17454.38 | G9: 0.3 | H9: =E9/F9 -> 0.090155594 | I9: =E9/SUM(E9:F9) -> 0.082699749 | J9: 0 | K9: =J9/(1+(1-G9)*H9) -> 0
B10: Medplus Health | D10: India | E10: =[1]Sheet1!P6 -> 1029.75 | F10: =[1]Sheet1!N6 -> 10021.96 | G10: 0.3 | H10: =E10/F10 -> 0.10274936 | I10: =E10/SUM(E10:F10) -> 0.093175626 | J10: 0.72 | K10: =J10/(1+(1-G10)*H10) -> 0.67168906
F13: Average | G13: =AVERAGE(G6:G10) -> 0.3 | H13: =AVERAGE(H6:H10) -> 0.10136843 | I13: =AVERAGE(I6:I10) -> 0.083973791 | J13: =AVERAGE(J6:J10) -> 0.86445622
F14: Median | G14: =MEDIAN(G6:G10) -> 0.3 | H14: =MEDIAN(H6:H10) -> 0.090155594 | I14: =MEDIAN(I6:I10) -> 0.082699749 | J14: =MEDIAN(J6:J10) -> 1.0622811

Sheet DCF MODELLING
B3: Weighted Average Cost Of Capital
B5: All figures are in INR unless stated otherwise
B7: Peer Comps
G9: Debt/ | H9: Debt/ | I9: Levered | J9: Unlevered
B10: Name of the Company | C10: Country | D10: Equity | E10: debt | F10: Tax Rate 1 | G10: Equity | H10: Capital | I10: Beta 2 | J10: Beta 3
B12: Avenue Super. | C12: India | D12: =[1]Sheet1!N2 -> 281370.49 | E12: =[1]Sheet1!P2 -> 712.91 | F12: 0.3 | G12: =E12/D12 -> 0.0025337056 | H12: =E12/(SUM(D12:E12)) -> 0.0025273022 | I12: ='PEER COMPARISON'!J6 -> 1.0622811 | J12: =I12/(1+(1-F12)*G12) -> 1.0604004
B13: Trent | C13: India | D13: =[1]Sheet1!N3 -> 185816.8 | E13: =[1]Sheet1!P3 -> 1842.2 | F13: 0.3 | G13: =E13/D13 -> 0.0099140659 | H13: =E13/(SUM(D13:E13)) -> 0.0098167421 | I13: ='PEER COMPARISON'!J7 -> 1.11 | J13: =I13/(1+(1-F13)*G13) -> 1.1023499
B14: Aditya Bir. Fas. | C14: India | D14: =[1]Sheet1!N4 -> 33165.94 | E14: =[1]Sheet1!P4 -> 9999.18 | F14: 0.3 | G14: =E14/D14 -> 0.30148942 | H14: =E14/(SUM(D14:E14)) -> 0.23164954 | I14: ='PEER COMPARISON'!J8 -> 1.43 | J14: =I14/(1+(1-F14)*G14) -> 1.1808007
B15: Brainbees Solut. | C15: India | D15: =[1]Sheet1!N5 -> 17454.38 | E15: =[1]Sheet1!P5 -> 1573.61 | F15: 0.3 | G15: =E15/D15 -> 0.090155594 | H15: =E15/(SUM(D15:E15)) -> 0.082699749 | I15: ='PEER COMPARISON'!J9 -> 0 | J15: =I15/(1+(1-F15)*G15) -> 0
B16: Medplus Health | C16: India | D16: =[1]Sheet1!N6 -> 10021.96 | E16: =[1]Sheet1!P6 -> 1029.75 | F16: 0.3 | G16: =E16/D16 -> 0.10274936 | H16: =E16/(SUM(D16:E16)) -> 0.093175626 | I16: ='PEER COMPARISON'!J10 -> 0.72 | J16: =I16/(1+(1-F16)*G16) -> 0.67168906
E20: AVERAGE | F20: =AVERAGE(F12:F16) -> 0.3 | G20: =AVERAGE(G12:G16) -> 0.10136843 | H20: =AVERAGE(H12:H16) -> 0.083973791 | I20: =AVERAGE(I12:I16) -> 0.86445622 | J20: =AVERAGE(J12:J16) -> 0.80304801
E21: MEDIAN | F21: =MEDIAN(F12:F16) -> 0.3 | G21: =MEDIAN(G12:G16) -> 0.090155594 | H21: =MEDIAN(H12:H16) -> 0.082699749 | I21: =MEDIAN(I12:I16) -> 1.0622811 | J21: =MEDIAN(J12:J16) -> 1.0604004
B24: Cost of Debt | J24: Cost Of Equity
B26: Pre-Tax Cost of Debt | C26: =58/C34 -> 0.081356693 | J26: Risk Free Rate | K26: 0.0647
B27: Tax Rate | C27: 0.3 | J27: Equity Risk Premium | K27: =[3]Sheet1!$G$4-K26 -> 0.088648
B28: Post-Tax Cost of Debt | C28: =C26*(1-C27) -> 0.056949685 | J28: Levered Beta 4 | K28: 1.12
J29: Cost Of Equity | K29: =K26+K27*K28 -> 0.16398576
B31: Capital Structure | J31: Cost Of Equity
D33: Current | E33: Target | J33: Comp. median unlevered Beta | K33: =J21 -> 1.0604004
B34: Total Debt | C34: =E12 -> 712.91 | D34: =C34/C36 -> 0.0025273022 | E34: =H20 -> 0.083973791 | J34: target debt/equity | K34: =E34 -> 0.083973791
B35: Market Capitalization | C35: =D12 -> 281370.49 | D35: =D36-D34 -> 0.9974727 | E35: =E36-E34 -> 0.91602621 | J35: Tax Rate | K35: 0.3
B36: Total Capital | C36: =SUM(C34:C35) -> 282083.4 | D36: 1 | E36: 1 | J36: Levered Beta | K36: =K33*(1+(1-K35)*K34) -> 1.1227324
B38: debt/equity | D38: =D34/D35 -> 0.0025337056 | E38: =E34/E35 -> 0.091671821
B43: Weighted Average Cost Of Capital | J43: Notes
J44: 1. Tax rate considered as marginal tax rate for the country
B45: Debt | C45: =C28 -> 0.056949685 | D45: =E34 -> 0.083973791 | J45: 2.levered beta is based on 5 year monthly data
B46: Equity | C46: =K29 -> 0.16398576 | D46: =E35 -> 0.91602621 | J46: 3.unlevered data = levered beta/(1+(1-tax rate)*debt/equity)
B47: Weighted Average Cost Of Capital | D47: =SUMPRODUCT(C45:C46,D45:D46) -> 0.15499754 | J47: 4.levered beta = unlevered beta*(1+(1-tax rate)* debt/equity)

Sheet BETA CALCULATION
A2: AVENUE SUPERMART | F2: NIFTY 50
A3: Date | B3: Price | C3: Weakly Return | F3: Price | G3: Weakly Return
A4: 45018 | B4: 3496.1 | F4: 17599.15
A5: 45025 | B5: 3501.05 | C5: =B5/B4-1 -> 0.0014158634 | F5: 17828 | G5: =F5/F4-1 -> 0.013003469 | J5: BETA DRIFTIG
A6: 45032 | B6: 3455.9 | C6: =B6/B5-1 -> -0.012896131 | F6: 17624.05 | G6: =F6/F5-1 -> -0.01143987
A7: 45039 | B7: 3511.95 | C7: =B7/B6-1 -> 0.016218641 | F7: 18065 | G7: =F7/F6-1 -> 0.025019788 | J7: LEVERED RAW BETA | L7: =Q7 -> 1.0622811 | O7: BETA1 | Q7: =SLOPE(C5:C108,G5:G108) -> 1.0622811
A8: 45046 | B8: 3598.2 | C8: =B8/B7-1 -> 0.024559006 | F8: 18069 | G8: =F8/F7-1 -> 0.00022142264 | J8: RAW BETA WEIGHT | L8: 0.75 | O8: BETA2 | Q8: =COVAR(C5:C108,G5:G108)/VAR(G5:G108) -> 1.0520668 | R8: Cov of xy/variance of
A9: 45053 | B9: 3677.55 | C9: =B9/B8-1 -> 0.022052693 | F9: 18314.8 | G9: =F9/F8-1 -> 0.013603409 | J9: MARKET BETA | L9: 1 | O9: BETA3 | Q9: =N120 -> 1.0622811
A10: 45060 | B10: 3395.25 | C10: =B10/B9-1 -> -0.076763062 | F10: 18203.4 | G10: =F10/F9-1 -> -0.0060825125 | J10: MARKET BETA WEIGHT | L10: 0.25
A11: 45067 | B11: 3501.75 | C11: =B11/B10-1 -> 0.031367351 | F11: 18499.35 | G11: =F11/F10-1 -> 0.016257952
A12: 45074 | B12: 3531.6 | C12: =B12/B11-1 -> 0.0085243093 | F12: 18534.1 | G12: =F12/F11-1 -> 0.0018784444 | J12: ADJUSTED BETA | L12: =(L7*L8)+(L10*L9) -> 1.0467108
A13: 45081 | B13: 3632.1 | C13: =B13/B12-1 -> 0.028457356 | F13: 18563.4 | G13: =F13/F12-1 -> 0.0015808699
A14: 45088 | B14: 4085.6 | C14: =B14/B13-1 -> 0.1248589 | F14: 18826 | G14: =F14/F13-1 -> 0.014146115
A15: 45095 | B15: 3744.05 | C15: =B15/B14-1 -> -0.083598492 | F15: 18665.5 | G15: =F15/F14-1 -> -0.0085254435
A16: 45102 | B16: 3889.2 | C16: =B16/B15-1 -> 0.038768179 | F16: 19189.05 | G16: =F16/F15-1 -> 0.028049074
A17: 45109 | B17: 3808.95 | C17: =B17/B16-1 -> -0.020634064 | F17: 19331.8 | G17: =F17/F16-1 -> 0.0074391385 | J17: SUMARY OUTPUT
A18: 45116 | B18: 3838.75 | C18: =B18/B17-1 -> 0.0078236784 | F18: 19564.5 | G18: =F18/F17-1 -> 0.012037162
A19: 45123 | B19: 3675.7 | C19: =B19/B18-1 -> -0.042474764 | F19: 19745 | G19: =F19/F18-1 -> 0.0092258938 | J19: REGRESSION STATISTICS
A20: 45130 | B20: 3713.9 | C20: =B20/B19-1 -> 0.010392578 | F20: 19646.05 | G20: =F20/F19-1 -> -0.0050113953
A21: 45137 | B21: 3652.1 | C21: =B21/B20-1 -> -0.01664019 | F21: 19517 | G21: =F21/F20-1 -> -0.0065687505
A22: 45144 | B22: 3550.05 | C22: =B22/B21-1 -> -0.027942827 | F22: 19428.3 | G22: =F22/F21-1 -> -0.0045447559 | Q22: SUMMARY OUTPUT
A23: 45151 | B23: 3540.95 | C23: =B23/B22-1 -> -0.0025633442 | F23: 19310.15 | G23: =F23/F22-1 -> -0.006081335
A24: 45158 | B24: 3534.6 | C24: =B24/B23-1 -> -0.0017933041 | F24: 19265.8 | G24: =F24/F23-1 -> -0.0022967196 | Q24: Regression Statistics
A25: 45165 | B25: 3761.05 | C25: =B25/B24-1 -> 0.064066655 | F25: 19435.3 | G25: =F25/F24-1 -> 0.0087979736 | Q25: Multiple R | R25: 0.41785324
A26: 45172 | B26: 3782.4 | C26: =B26/B25-1 -> 0.0056766063 | F26: 19819.95 | G26: =F26/F25-1 -> 0.019791308 | Q26: R Square | R26: 0.17460133
A27: 45179 | B27: 3796 | C27: =B27/B26-1 -> 0.0035956007 | F27: 20192.35 | G27: =F27/F26-1 -> 0.018789149 | Q27: Adjusted R Square | R27: 0.16650918
A28: 45186 | B28: 3689.1 | C28: =B28/B27-1 -> -0.028161222 | F28: 19674.25 | G28: =F28/F27-1 -> -0.025658232 | Q28: Standard Error | R28: 0.037973143
A29: 45193 | B29: 3675.6 | C29: =B29/B28-1 -> -0.0036594291 | F29: 19638.3 | G29: =F29/F28-1 -> -0.0018272615 | Q29: Observations | R29: 104
A30: 45200 | B30: 3833.95 | C30: =B30/B29-1 -> 0.043081402 | F30: 19653.5 | G30: =F30/F29-1 -> 0.00077399775
A31: 45207 | B31: 3935.85 | C31: =B31/B30-1 -> 0.026578333 | F31: 19751.05 | G31: =F31/F30-1 -> 0.0049634925 | Q31: ANOVA
A32: 45214 | B32: 3749.5 | C32: =B32/B31-1 -> -0.047346825 | F32: 19542.65 | G32: =F32/F31-1 -> -0.010551338 | R32: df | S32: SS | T32: MS | U32: F | V32: Significance F
A33: 45221 | B33: 3665.45 | C33: =B33/B32-1 -> -0.022416322 | F33: 19047.25 | G33: =F33/F32-1 -> -0.025349684 | Q33: Regression | R33: 1 | S33: 0.031112652 | T33: 0.031112652 | U33: 21.576646 | V33: 1.0173947e-05
A34: 45228 | B34: 3649.7 | C34: =B34/B33-1 -> -0.0042968803 | F34: 19230.6 | G34: =F34/F33-1 -> 0.0096260615 | Q34: Residual | R34: 102 | S34: 0.14707988 | T34: 0.0014419596
A35: 45235 | B35: 3798.4 | C35: =B35/B34-1 -> 0.040743075 | F35: 19425.35 | G35: =F35/F34-1 -> 0.010127089 | Q35: Total | R35: 103 | S35: 0.17819253
A36: 45242 | B36: 3810.9 | C36: =B36/B35-1 -> 0.0032908593 | F36: 19731.8 | G36: =F36/F35-1 -> 0.015775778
A37: 45249 | B37: 3842.9 | C37: =B37/B36-1 -> 0.0083969666 | F37: 19794.7 | G37: =F37/F36-1 -> 0.0031877477 | R37: Coefficients | S37: Standard Error | T37: t Stat | U37: P-value | V37: Lower 95% | W37: Upper 95% | X37: Lower 95.0% | Y37: Upper 95.0%
A38: 45256 | B38: 3988.4 | C38: =B38/B37-1 -> 0.037862031 | F38: 20267.9 | G38: =F38/F37-1 -> 0.023905389 | Q38: Intercept | R38: -0.00058993947 | S38: 0.0037732939 | T38: -0.15634602 | U38: 0.87606931 | V38: -0.0080742498 | W38: 0.0068943708 | X38: -0.0080742498 | Y38: 0.0068943708
A39: 45263 | B39: 4070.65 | C39: =B39/B38-1 -> 0.020622305 | F39: 20969.4 | G39: =F39/F38-1 -> 0.034611381 | Q39: X Variable 1 | R39: 1.0622811 | S39: 0.22869016 | T39: 4.6450669 | U39: 1.0173947e-05 | V39: 0.60867525 | W39: 1.5158869 | X39: 0.60867525 | Y39: 1.5158869
A40: 45270 | B40: 4045.65 | C40: =B40/B39-1 -> -0.0061415253 | F40: 21456.65 | G40: =F40/F39-1 -> 0.023236239
A41: 45277 | B41: 4007.95 | C41: =B41/B40-1 -> -0.0093186509 | F41: 21349.4 | G41: =F41/F40-1 -> -0.0049984504
A42: 45284 | B42: 4082.65 | C42: =B42/B41-1 -> 0.018637957 | F42: 21731.4 | G42: =F42/F41-1 -> 0.017892775
A43: 45291 | B43: 3863.5 | C43: =B43/B42-1 -> -0.053678371 | F43: 21710.8 | G43: =F43/F42-1 -> -0.00094793709
A44: 45298 | B44: 3841 | C44: =B44/B43-1 -> -0.005823735 | F44: 21894.55 | G44: =F44/F43-1 -> 0.0084635297
A45: 45305 | B45: 3731.7 | C45: =B45/B44-1 -> -0.028456131 | F45: 21622.4 | G45: =F45/F44-1 -> -0.012430034
A46: 45312 | B46: 3734.25 | C46: =B46/B45-1 -> 0.00068333467 | F46: 21352.6 | G46: =F46/F45-1 -> -0.012477801
A47: 45319 | B47: 3784.3 | C47: =B47/B46-1 -> 0.013402959 | F47: 21853.8 | G47: =F47/F46-1 -> 0.023472551
A48: 45326 | B48: 3719.2 | C48: =B48/B47-1 -> -0.017202653 | F48: 21782.5 | G48: =F48/F47-1 -> -0.0032625905
A49: 45333 | B49: 3693.3 | C49: =B49/B48-1 -> -0.0069638632 | F49: 22040.7 | G49: =F49/F48-1 -> 0.011853552
A50: 45340 | B50: 3840.55 | C50: =B50/B49-1 -> 0.039869493 | F50: 22212.7 | G50: =F50/F49-1 -> 0.0078037449
A51: 45347 | B51: 3884.15 | C51: =B51/B50-1 -> 0.011352541 | F51: 22338.75 | G51: =F51/F50-1 -> 0.0056746816
... A102: 45704 | B102: 3596.7 | C102: =B102/B101-1 -> -0.023339172 | F102: 22795.9 | G102: =F102/F101-1 -> -0.0058157157
A103: 45711 | B103: 3403.95 | C103: =B103/B102-1 -> -0.053590792 | F103: 22124.7 | G103: =F103/F102-1 -> -0.029443891 | M103: SUMMARY OUTPUT
A104: 45718 | B104: 3593.6 | C104: =B104/B103-1 -> 0.055714684 | F104: 22552.5 | G104: =F104/F103-1 -> 0.019335855
A105: 45725 | B105: 3797.1 | C105: =B105/B104-1 -> 0.056628451 | F105: 22397.2 | G105: =F105/F104-1 -> -0.0068861545 | M105: Regression Statistics
A106: 45732 | B106: 3892.2 | C106: =B106/B105-1 -> 0.025045429 | F106: 23350.4 | G106: =F106/F105-1 -> 0.042558891 | M106: Multiple R | N106: 0.41785324
A107: 45739 | B107: 4083.2 | C107: =B107/B106-1 -> 0.049072504 | F107: 23519.35 | G107: =F107/F106-1 -> 0.0072354221 | M107: R Square | N107: 0.17460133
A108: 45746 | B108: 4039.9 | C108: =B108/B107-1 -> -0.010604428 | F108: 22904.45 | G108: =F108/F107-1 -> -0.02614443 | M108: Adjusted R Square | N108: 0.16650918
M109: Standard Error | N109: 0.037973143
M110: Observations | N110: 104
M112: ANOVA
N113: df | O113: SS | P113: MS | Q113: F | R113: Significance F
M114: Regression | N114: 1 | O114: 0.031112652 | P114: 0.031112652 | Q114: 21.576646 | R114: 1.0173947e-05
M115: Residual | N115: 102 | O115: 0.14707988 | P115: 0.0014419596
M116: Total | N116: 103 | O116: 0.17819253
N118: Coefficients | O118: Standard Error | P118: t Stat | Q118: P-value | R118: Lower 95% | S118: Upper 95% | T118: Lower 95.0% | U118: Upper 95.0%
M119: Intercept | N119: -0.00058993947 | O119: 0.0037732939 | P119: -0.15634602 | Q119: 0.87606931 | R119: -0.0080742498 | S119: 0.0068943708 | T119: -0.0080742498 | U119: 0.0068943708
M120: X Variable 1 | N120: 1.0622811 | O120: 0.22869016 | P120: 4.6450669 | Q120: 1.0173947e-05 | R120: 0.60867525 | S120: 1.5158869 | T120: 0.60867525 | U120: 1.5158869

Sheet BETA CALCULATION (2)
A2: AVENUE SUPERMART | F2: NIFTY 50
A3: Date | B3: Price | C3: Weakly Return | F3: Price | G3: Weakly Return
A4: 45018 | B4: 3496.1 | F4: 17599.15
A5: 45025 | B5: 3501.05 | C5: =B5/B4-1 -> 0.0014158634 | F5: 17828 | G5: =F5/F4-1 -> 0.013003469 | J5: BETA DRIFTIG
A6: 45032 | B6: 3455.9 | C6: =B6/B5-1 -> -0.012896131 | F6: 17624.05 | G6: =F6/F5-1 -> -0.01143987
A7: 45039 | B7: 3511.95 | C7: =B7/B6-1 -> 0.016218641 | F7: 18065 | G7: =F7/F6-1 -> 0.025019788 | J7: LEVERED RAW BETA | L7: =Q7 -> 1.0622811 | O7: BETA1 | Q7: =SLOPE(C5:C108,G5:G108) -> 1.0622811
A8: 45046 | B8: 3598.2 | C8: =B8/B7-1 -> 0.024559006 | F8: 18069 | G8: =F8/F7-1 -> 0.00022142264 | J8: RAW BETA WEIGHT | L8: 0.75 | O8: BETA2 | Q8: =COVAR(C5:C108,G5:G108)/VAR(G5:G108) -> 1.0520668 | R8: Cov of xy/variance of
A9: 45053 | B9: 3677.55 | C9: =B9/B8-1 -> 0.022052693 | F9: 18314.8 | G9: =F9/F8-1 -> 0.013603409 | J9: MARKET BETA | L9: 1 | O9: BETA3 | Q9: =N120 -> 1.0622811
A10: 45060 | B10: 3395.25 | C10: =B10/B9-1 -> -0.076763062 | F10: 18203.4 | G10: =F10/F9-1 -> -0.0060825125 | J10: MARKET BETA WEIGHT | L10: 0.25
A11: 45067 | B11: 3501.75 | C11: =B11/B10-1 -> 0.031367351 | F11: 18499.35 | G11: =F11/F10-1 -> 0.016257952
A12: 45074 | B12: 3531.6 | C12: =B12/B11-1 -> 0.0085243093 | F12: 18534.1 | G12: =F12/F11-1 -> 0.0018784444 | J12: ADJUSTED BETA | L12: =(L7*L8)+(L10*L9) -> 1.0467108
A13: 45081 | B13: 3632.1 | C13: =B13/B12-1 -> 0.028457356 | F13: 18563.4 | G13: =F13/F12-1 -> 0.0015808699
A14: 45088 | B14: 4085.6 | C14: =B14/B13-1 -> 0.1248589 | F14: 18826 | G14: =F14/F13-1 -> 0.014146115
A15: 45095 | B15: 3744.05 | C15: =B15/B14-1 -> -0.083598492 | F15: 18665.5 | G15: =F15/F14-1 -> -0.0085254435
A16: 45102 | B16: 3889.2 | C16: =B16/B15-1 -> 0.038768179 | F16: 19189.05 | G16: =F16/F15-1 -> 0.028049074
A17: 45109 | B17: 3808.95 | C17: =B17/B16-1 -> -0.020634064 | F17: 19331.8 | G17: =F17/F16-1 -> 0.0074391385 | J17: SUMARY OUTPUT
A18: 45116 | B18: 3838.75 | C18: =B18/B17-1 -> 0.0078236784 | F18: 19564.5 | G18: =F18/F17-1 -> 0.012037162
A19: 45123 | B19: 3675.7 | C19: =B19/B18-1 -> -0.042474764 | F19: 19745 | G19: =F19/F18-1 -> 0.0092258938 | J19: REGRESSION STATISTICS
A20: 45130 | B20: 3713.9 | C20: =B20/B19-1 -> 0.010392578 | F20: 19646.05 | G20: =F20/F19-1 -> -0.0050113953
A21: 45137 | B21: 3652.1 | C21: =B21/B20-1 -> -0.01664019 | F21: 19517 | G21: =F21/F20-1 -> -0.0065687505
A22: 45144 | B22: 3550.05 | C22: =B22/B21-1 -> -0.027942827 | F22: 19428.3 | G22: =F22/F21-1 -> -0.0045447559 | Q22: SUMMARY OUTPUT
A23: 45151 | B23: 3540.95 | C23: =B23/B22-1 -> -0.0025633442 | F23: 19310.15 | G23: =F23/F22-1 -> -0.006081335
A24: 45158 | B24: 3534.6 | C24: =B24/B23-1 -> -0.0017933041 | F24: 19265.8 | G24: =F24/F23-1 -> -0.0022967196 | Q24: Regression Statistics
A25: 45165 | B25: 3761.05 | C25: =B25/B24-1 -> 0.064066655 | F25: 19435.3 | G25: =F25/F24-1 -> 0.0087979736 | Q25: Multiple R | R25: 0.41785324
A26: 45172 | B26: 3782.4 | C26: =B26/B25-1 -> 0.0056766063 | F26: 19819.95 | G26: =F26/F25-1 -> 0.019791308 | Q26: R Square | R26: 0.17460133
A27: 45179 | B27: 3796 | C27: =B27/B26-1 -> 0.0035956007 | F27: 20192.35 | G27: =F27/F26-1 -> 0.018789149 | Q27: Adjusted R Square | R27: 0.16650918
A28: 45186 | B28: 3689.1 | C28: =B28/B27-1 -> -0.028161222 | F28: 19674.25 | G28: =F28/F27-1 -> -0.025658232 | Q28: Standard Error | R28: 0.037973143
A29: 45193 | B29: 3675.6 | C29: =B29/B28-1 -> -0.0036594291 | F29: 19638.3 | G29: =F29/F28-1 -> -0.0018272615 | Q29: Observations | R29: 104
A30: 45200 | B30: 3833.95 | C30: =B30/B29-1 -> 0.043081402 | F30: 19653.5 | G30: =F30/F29-1 -> 0.00077399775
A31: 45207 | B31: 3935.85 | C31: =B31/B30-1 -> 0.026578333 | F31: 19751.05 | G31: =F31/F30-1 -> 0.0049634925 | Q31: ANOVA
A32: 45214 | B32: 3749.5 | C32: =B32/B31-1 -> -0.047346825 | F32: 19542.65 | G32: =F32/F31-1 -> -0.010551338 | R32: df | S32: SS | T32: MS | U32: F | V32: Significance F
A33: 45221 | B33: 3665.45 | C33: =B33/B32-1 -> -0.022416322 | F33: 19047.25 | G33: =F33/F32-1 -> -0.025349684 | Q33: Regression | R33: 1 | S33: 0.031112652 | T33: 0.031112652 | U33: 21.576646 | V33: 1.0173947e-05
A34: 45228 | B34: 3649.7 | C34: =B34/B33-1 -> -0.0042968803 | F34: 19230.6 | G34: =F34/F33-1 -> 0.0096260615 | Q34: Residual | R34: 102 | S34: 0.14707988 | T34: 0.0014419596
A35: 45235 | B35: 3798.4 | C35: =B35/B34-1 -> 0.040743075 | F35: 19425.35 | G35: =F35/F34-1 -> 0.010127089 | Q35: Total | R35: 103 | S35: 0.17819253
A36: 45242 | B36: 3810.9 | C36: =B36/B35-1 -> 0.0032908593 | F36: 19731.8 | G36: =F36/F35-1 -> 0.015775778
A37: 45249 | B37: 3842.9 | C37: =B37/B36-1 -> 0.0083969666 | F37: 19794.7 | G37: =F37/F36-1 -> 0.0031877477 | R37: Coefficients | S37: Standard Error | T37: t Stat | U37: P-value | V37: Lower 95% | W37: Upper 95% | X37: Lower 95.0% | Y37: Upper 95.0%
A38: 45256 | B38: 3988.4 | C38: =B38/B37-1 -> 0.037862031 | F38: 20267.9 | G38: =F38/F37-1 -> 0.023905389 | Q38: Intercept | R38: -0.00058993947 | S38: 0.0037732939 | T38: -0.15634602 | U38: 0.87606931 | V38: -0.0080742498 | W38: 0.0068943708 | X38: -0.0080742498 | Y38: 0.0068943708
A39: 45263 | B39: 4070.65 | C39: =B39/B38-1 -> 0.020622305 | F39: 20969.4 | G39: =F39/F38-1 -> 0.034611381 | Q39: X Variable 1 | R39: 1.0622811 | S39: 0.22869016 | T39: 4.6450669 | U39: 1.0173947e-05 | V39: 0.60867525 | W39: 1.5158869 | X39: 0.60867525 | Y39: 1.5158869
A40: 45270 | B40: 4045.65 | C40: =B40/B39-1 -> -0.0061415253 | F40: 21456.65 | G40: =F40/F39-1 -> 0.023236239
A41: 45277 | B41: 4007.95 | C41: =B41/B40-1 -> -0.0093186509 | F41: 21349.4 | G41: =F41/F40-1 -> -0.0049984504
A42: 45284 | B42: 4082.65 | C42: =B42/B41-1 -> 0.018637957 | F42: 21731.4 | G42: =F42/F41-1 -> 0.017892775
A43: 45291 | B43: 3863.5 | C43: =B43/B42-1 -> -0.053678371 | F43: 21710.8 | G43: =F43/F42-1 -> -0.00094793709
A44: 45298 | B44: 3841 | C44: =B44/B43-1 -> -0.005823735 | F44: 21894.55 | G44: =F44/F43-1 -> 0.0084635297
A45: 45305 | B45: 3731.7 | C45: =B45/B44-1 -> -0.028456131 | F45: 21622.4 | G45: =F45/F44-1 -> -0.012430034
A46: 45312 | B46: 3734.25 | C46: =B46/B45-1 -> 0.00068333467 | F46: 21352.6 | G46: =F46/F45-1 -> -0.012477801
A47: 45319 | B47: 3784.3 | C47: =B47/B46-1 -> 0.013402959 | F47: 21853.8 | G47: =F47/F46-1 -> 0.023472551
A48: 45326 | B48: 3719.2 | C48: =B48/B47-1 -> -0.017202653 | F48: 21782.5 | G48: =F48/F47-1 -> -0.0032625905
A49: 45333 | B49: 3693.3 | C49: =B49/B48-1 -> -0.0069638632 | F49: 22040.7 | G49: =F49/F48-1 -> 0.011853552
A50: 45340 | B50: 3840.55 | C50: =B50/B49-1 -> 0.039869493 | F50: 22212.7 | G50: =F50/F49-1 -> 0.0078037449
A51: 45347 | B51: 3884.15 | C51: =B51/B50-1 -> 0.011352541 | F51: 22338.75 | G51: =F51/F50-1 -> 0.0056746816
... A102: 45704 | B102: 3596.7 | C102: =B102/B101-1 -> -0.023339172 | F102: 22795.9 | G102: =F102/F101-1 -> -0.0058157157
A103: 45711 | B103: 3403.95 | C103: =B103/B102-1 -> -0.053590792 | F103: 22124.7 | G103: =F103/F102-1 -> -0.029443891 | M103: SUMMARY OUTPUT
A104: 45718 | B104: 3593.6 | C104: =B104/B103-1 -> 0.055714684 | F104: 22552.5 | G104: =F104/F103-1 -> 0.019335855
A105: 45725 | B105: 3797.1 | C105: =B105/B104-1 -> 0.056628451 | F105: 22397.2 | G105: =F105/F104-1 -> -0.0068861545 | M105: Regression Statistics
A106: 45732 | B106: 3892.2 | C106: =B106/B105-1 -> 0.025045429 | F106: 23350.4 | G106: =F106/F105-1 -> 0.042558891 | M106: Multiple R | N106: 0.41785324
A107: 45739 | B107: 4083.2 | C107: =B107/B106-1 -> 0.049072504 | F107: 23519.35 | G107: =F107/F106-1 -> 0.0072354221 | M107: R Square | N107: 0.17460133
A108: 45746 | B108: 4039.9 | C108: =B108/B107-1 -> -0.010604428 | F108: 22904.45 | G108: =F108/F107-1 -> -0.02614443 | M108: Adjusted R Square | N108: 0.16650918
M109: Standard Error | N109: 0.037973143
M110: Observations | N110: 104
M112: ANOVA
N113: df | O113: SS | P113: MS | Q113: F | R113: Significance F
M114: Regression | N114: 1 | O114: 0.031112652 | P114: 0.031112652 | Q114: 21.576646 | R114: 1.0173947e-05
M115: Residual | N115: 102 | O115: 0.14707988 | P115: 0.0014419596
M116: Total | N116: 103 | O116: 0.17819253
N118: Coefficients | O118: Standard Error | P118: t Stat | Q118: P-value | R118: Lower 95% | S118: Upper 95% | T118: Lower 95.0% | U118: Upper 95.0%
M119: Intercept | N119: -0.00058993947 | O119: 0.0037732939 | P119: -0.15634602 | Q119: 0.87606931 | R119: -0.0080742498 | S119: 0.0068943708 | T119: -0.0080742498 | U119: 0.0068943708
M120: X Variable 1 | N120: 1.0622811 | O120: 0.22869016 | P120: 4.6450669 | Q120: 1.0173947e-05 | R120: 0.60867525 | S120: 1.5158869 | T120: 0.60867525 | U120: 1.5158869
